Workbook

Sheet PRINTING
B1: INVENTORY REPORT
B2: AS OF JUNE 2026
B3: PRINTING
B5: SHELF NO. | C5: SHELF DESCRIPTION | D5: BARCODE/ CONTROL NUMBER | E5: PRODUCT NAME | F5: UNIT COST | G5: QUANTITY PER RECORD / ACCPOS | H5: ACTUAL INVENTORY | I5: TOTAL COST - RECORD | J5: TOTAL COST - ACTUAL INVENTORY | K5: VARIANCE - QUANTITY | L5: VARIANCE - COST | M5: REMARKS / CAUSE OF VARIANCE
B6: 20 | C6: OFFICE SUPPLIES | D6: 70002 | E6: PRINTING ADRITE RIBBON INK MEDIUM/BLACK | F6: 13.50 | G6: 253 | H6: 253 | I6: =F6*G6 -> 3415.5 | J6: =F6*H6 -> 3415.5 | K6: =G6-H6 -> 0 | L6: =I6-J6 -> 0
B7: 20 | C7: OFFICE SUPPLIES | D7: 70180 | E7: PRINTING ADVENTURE PLASTIC ENVELOPE LONG | F7: 18.00 | G7: 53 | H7: 53 | I7: =F7*G7 -> 954 | J7: =F7*H7 -> 954 | K7: =G7-H7 -> 0 | L7: =I7-J7 -> 0
B8: 20 | C8: OFFICE SUPPLIES | D8: 70181 | E8: PRINTING ADVENTURE PLASTIC ENVELOPE W/ HANDLE LONG | F8: 45.00 | G8: 4 | H8: 4 | I8: =F8*G8 -> 180 | J8: =F8*H8 -> 180 | K8: =G8-H8 -> 0 | L8: =I8-J8 -> 0
B9: 20 | C9: OFFICE SUPPLIES | D9: 70003 | E9: PRINTING ARTLINE HIGHLIGHTER ORANGE | F9: 30.00 | G9: 5 | H9: 5 | I9: =F9*G9 -> 150 | J9: =F9*H9 -> 150 | K9: =G9-H9 -> 0 | L9: =I9-J9 -> 0
B10: 20 | C10: OFFICE SUPPLIES | D10: 70006 | E10: PRINTING ASIAN COLOR BONDPAPER BLUE SHORT | F10: 120.00 | G10: 5 | H10: 5 | I10: =F10*G10 -> 600 | J10: =F10*H10 -> 600 | K10: =G10-H10 -> 0 | L10: =I10-J10 -> 0
B11: 20 | C11: OFFICE SUPPLIES | D11: 70007 | E11: PRINTING ASIAN COLOR BONDPAPER PINK SHORT | F11: 120.00 | G11: 3 | H11: 3 | I11: =F11*G11 -> 360 | J11: =F11*H11 -> 360 | K11: =G11-H11 -> 0 | L11: =I11-J11 -> 0
B12: 20 | C12: OFFICE SUPPLIES | D12: 70212 | E12: PRINTING ASKI MPC BOD & GA TARPAULIN 1.5X2FT | F12: 36.00 | G12: 2 | H12: 2 | I12: =F12*G12 -> 72 | J12: =F12*H12 -> 72 | K12: =G12-H12 -> 0 | L12: =I12-J12 -> 0
B13: 20 | C13: OFFICE SUPPLIES | D13: 70008 | E13: PRINTING ASSORTED PLASTIC SLIDING FOLDER LONG | F13: 4.00 | G13: 27 | H13: 27 | I13: =F13*G13 -> 108 | J13: =F13*H13 -> 108 | K13: =G13-H13 -> 0 | L13: =I13-J13 -> 0
B14: 20 | C14: OFFICE SUPPLIES | D14: 70009 | E14: PRINTING ASSORTED PLASTIC SLIDING FOLDER SHORT | F14: 3.75 | G14: 68 | H14: 68 | I14: =F14*G14 -> 255 | J14: =F14*H14 -> 255 | K14: =G14-H14 -> 0 | L14: =I14-J14 -> 0
B15: 20 | C15: OFFICE SUPPLIES | D15: 70278 | E15: PRINTING BALIK TANGKILIK CARD | F15: 105.00 | G15: 157 | H15: 157 | I15: =F15*G15 -> 16485 | J15: =F15*H15 -> 16485 | K15: =G15-H15 -> 0 | L15: =I15-J15 -> 0
B16: 20 | C16: OFFICE SUPPLIES | D16: 70010 | E16: PRINTING BALLPEN HBW GREEN | F16: 3.50 | G16: 55 | H16: 55 | I16: =F16*G16 -> 192.5 | J16: =F16*H16 -> 192.5 | K16: =G16-H16 -> 0 | L16: =I16-J16 -> 0
B17: 20 | C17: OFFICE SUPPLIES | D17: 70011 | E17: PRINTING BALLPEN HBW MATRIX BLUE | F17: 3.50 | G17: 1 | H17: 1 | I17: =F17*G17 -> 3.5 | J17: =F17*H17 -> 3.5 | K17: =G17-H17 -> 0 | L17: =I17-J17 -> 0
... B78: 20 | C78: OFFICE SUPPLIES | D78: 70323 | E78: PRINTING EXPANDING FOLDER LONG-2 | F78: 16.00 | G78: 200 | H78: 200 | I78: =F78*G78 -> 3200 | J78: =F78*H78 -> 3200 | K78: =G78-H78 -> 0 | L78: =I78-J78 -> 0
B79: 20 | C79: OFFICE SUPPLIES | D79: 70311 | E79: PRINTING EXPANDING FOLDER GREEN LONG - 2 | F79: 16.00 | G79: 147 | H79: 147 | I79: =F79*G79 -> 2352 | J79: =F79*H79 -> 2352 | K79: =G79-H79 -> 0 | L79: =I79-J79 -> 0
B80: 20 | C80: OFFICE SUPPLIES | D80: 70066 | E80: PRINTING EXPANDING FOLDER GREEN SHORT | F80: 14.50 | G80: 233 | H80: 233 | I80: =F80*G80 -> 3378.5 | J80: =F80*H80 -> 3378.5 | K80: =G80-H80 -> 0 | L80: =I80-J80 -> 0
B81: 20 | C81: OFFICE SUPPLIES | D81: 70067 | E81: PRINTING EXPANDING FOLDER LIGHT BLUE LONG | F81: 12.00 | G81: 222 | H81: 222 | I81: =F81*G81 -> 2664 | J81: =F81*H81 -> 2664 | K81: =G81-H81 -> 0 | L81: =I81-J81 -> 0
B82: 20 | C82: OFFICE SUPPLIES | D82: 70068 | E82: PRINTING EXPANDING FOLDER ORANGE LONG | F82: 13.50 | G82: 55 | H82: 55 | I82: =F82*G82 -> 742.5 | J82: =F82*H82 -> 742.5 | K82: =G82-H82 -> 0 | L82: =I82-J82 -> 0
B83: 20 | C83: OFFICE SUPPLIES | D83: 70069 | E83: PRINTING EXPANDING FOLDER PINK LONG | F83: 14.50 | G83: 10 | H83: 10 | I83: =F83*G83 -> 145 | J83: =F83*H83 -> 145 | K83: =G83-H83 -> 0 | L83: =I83-J83 -> 0
B84: 20 | C84: OFFICE SUPPLIES | D84: 70322 | E84: PRINTING EXPANDING FOLDER PINK LONG -2 | F84: 16.00 | G84: 200 | H84: 200 | I84: =F84*G84 -> 3200 | J84: =F84*H84 -> 3200 | K84: =G84-H84 -> 0 | L84: =I84-J84 -> 0
B85: 20 | C85: OFFICE SUPPLIES | D85: 70070 | E85: PRINTING EXPANDING FOLDER PINK SHORT | F85: 13.25 | G85: 1 | H85: 1 | I85: =F85*G85 -> 13.25 | J85: =F85*H85 -> 13.25 | K85: =G85-H85 -> 0 | L85: =I85-J85 -> 0
B86: 20 | C86: OFFICE SUPPLIES | D86: 70297 | E86: PRINTING EXPANDING FOLDER PINK SHORT - 2 | F86: 14.00 | G86: 100 | H86: 100 | I86: =F86*G86 -> 1400 | J86: =F86*H86 -> 1400 | K86: =G86-H86 -> 0 | L86: =I86-J86 -> 0
B87: 20 | C87: OFFICE SUPPLIES | D87: 70071 | E87: PRINTING EXPANDING FOLDER RED LONG | F87: 14.50 | G87: 23 | H87: 23 | I87: =F87*G87 -> 333.5 | J87: =F87*H87 -> 333.5 | K87: =G87-H87 -> 0 | L87: =I87-J87 -> 0
B88: 20 | C88: OFFICE SUPPLIES | D88: 70072 | E88: PRINTING EXPANDING FOLDER RED SHORT | F88: 13.25 | G88: 115 | H88: 115 | I88: =F88*G88 -> 1523.75 | J88: =F88*H88 -> 1523.75 | K88: =G88-H88 -> 0 | L88: =I88-J88 -> 0
B89: 20 | C89: OFFICE SUPPLIES | D89: 70073 | E89: PRINTING EXPANDING FOLDER ROYAL BLUE LONG | F89: 14.50 | G89: 67 | H89: 67 | I89: =F89*G89 -> 971.5 | J89: =F89*H89 -> 971.5 | K89: =G89-H89 -> 0 | L89: =I89-J89 -> 0
B90: 20 | C90: OFFICE SUPPLIES | D90: 70312 | E90: PRINTING EXPANDING FOLDER ROYAL BLUE LONG - 2 | F90: 16.00 | G90: 280 | H90: 280 | I90: =F90*G90 -> 4480 | J90: =F90*H90 -> 4480 | K90: =G90-H90 -> 0 | L90: =I90-J90 -> 0
B91: 20 | C91: OFFICE SUPPLIES | D91: 70313 | E91: PRINTING EXPANDING FOLDER ROYAL BLUE SHORT - 2 | F91: 15.00 | G91: 46 | H91: 46 | I91: =F91*G91 -> 690 | J91: =F91*H91 -> 690 | K91: =G91-H91 -> 0 | L91: =I91-J91 -> 0
... B93: 20 | C93: OFFICE SUPPLIES | D93: 70077 | E93: PRINTING FASTENER GATOR 8 1/2 SIZE | F93: 130.00 | G93: 48 | H93: 48 | I93: =F93*G93 -> 6240 | J93: =F93*H93 -> 6240 | K93: =G93-H93 -> 0 | L93: =I93-J93 -> 0
B94: 20 | C94: OFFICE SUPPLIES | D94: 70075 | E94: PRINTING FASTENER HOT ARTS 70MM | F94: 40.00 | G94: 219 | H94: 219 | I94: =F94*G94 -> 8760 | J94: =F94*H94 -> 8760 | K94: =G94-H94 -> 0 | L94: =I94-J94 -> 0
B95: 20 | C95: OFFICE SUPPLIES | D95: 70234 | E95: PRINTING FFNE POLO SHIRT M-2XL | F95: 281.11 | G95: 1 | H95: 1 | I95: =F95*G95 -> 281.11 | J95: =F95*H95 -> 281.11 | K95: =G95-H95 -> 0 | L95: =I95-J95 -> 0
B96: 20 | C96: OFFICE SUPPLIES | D96: 70249 | E96: PRINTING FILE BOX | F96: 98.00 | G96: 15 | H96: 15 | I96: =F96*G96 -> 1470 | J96: =F96*H96 -> 1470 | K96: =G96-H96 -> 0 | L96: =I96-J96 -> 0
B97: 20 | C97: OFFICE SUPPLIES | D97: 70078 | E97: PRINTING FILE RACK | F97: 98.00 | G97: 7 | H97: 7 | I97: =F97*G97 -> 686 | J97: =F97*H97 -> 686 | K97: =G97-H97 -> 0 | L97: =I97-J97 -> 0
B98: 20 | C98: OFFICE SUPPLIES | D98: 70079 | E98: PRINTING FOLDER BROWN SHORT | F98: 4.50 | G98: 495 | H98: 495 | I98: =F98*G98 -> 2227.5 | J98: =F98*H98 -> 2227.5 | K98: =G98-H98 -> 0 | L98: =I98-J98 -> 0
B99: 20 | C99: OFFICE SUPPLIES | D99: 70080 | E99: PRINTING FOLDER LONG BLUE | F99: 8.25 | G99: 649 | H99: 649 | I99: =F99*G99 -> 5354.25 | J99: =F99*H99 -> 5354.25 | K99: =G99-H99 -> 0 | L99: =I99-J99 -> 0
B100: 20 | C100: OFFICE SUPPLIES | D100: 70081 | E100: PRINTING FOLDER LONG GREEN | F100: 8.25 | G100: 1001 | H100: 1001 | I100: =F100*G100 -> 8258.25 | J100: =F100*H100 -> 8258.25 | K100: =G100-H100 -> 0 | L100: =I100-J100 -> 0
B101: 20 | C101: OFFICE SUPPLIES | D101: 70266 | E101: PRINTING FOLDER LONG ORANGE | F101: 7.00 | G101: 100 | H101: 100 | I101: =F101*G101 -> 700 | J101: =F101*H101 -> 700 | K101: =G101-H101 -> 0 | L101: =I101-J101 -> 0
B102: 20 | C102: OFFICE SUPPLIES | D102: 70082 | E102: PRINTING FOLDER LONG PINK | F102: 4.75 | G102: 806 | H102: 806 | I102: =F102*G102 -> 3828.5 | J102: =F102*H102 -> 3828.5 | K102: =G102-H102 -> 0 | L102: =I102-J102 -> 0
B103: 20 | C103: OFFICE SUPPLIES | D103: 70083 | E103: PRINTING FOLDER LONG RED | F103: 8.00 | G103: 236 | H103: 236 | I103: =F103*G103 -> 1888 | J103: =F103*H103 -> 1888 | K103: =G103-H103 -> 0 | L103: =I103-J103 -> 0
B104: 20 | C104: OFFICE SUPPLIES | D104: 70084 | E104: PRINTING FOLDER LONG VIOLET | F104: 4.75 | G104: 288 | H104: 288 | I104: =F104*G104 -> 1368 | J104: =F104*H104 -> 1368 | K104: =G104-H104 -> 0 | L104: =I104-J104 -> 0
B105: 20 | C105: OFFICE SUPPLIES | D105: 70085 | E105: PRINTING FOLDER LONG WHITE | F105: 2.70 | G105: 2294 | H105: 2760 | I105: =F105*G105 -> 6193.8 | J105: =F105*H105 -> 7452 | K105: =G105-H105 -> -466 | L105: =I105-J105 -> -1258.2
B106: 20 | C106: OFFICE SUPPLIES | D106: 70086 | E106: PRINTING FOLDER LONG YELLOW | F106: 8.25 | G106: 390 | H106: 390 | I106: =F106*G106 -> 3217.5 | J106: =F106*H106 -> 3217.5 | K106: =G106-H106 -> 0 | L106: =I106-J106 -> 0
... B116: 20 | C116: OFFICE SUPPLIES | D116: 70090 | E116: PRINTING FULLMARK INK FILM | F116: 400.00 | G116: 1 | H116: 1 | I116: =F116*G116 -> 400 | J116: =F116*H116 -> 400 | K116: =G116-H116 -> 0 | L116: =I116-J116 -> 0
B117: 20 | C117: OFFICE SUPPLIES | D117: 70306 | E117: PRINTING GATOR CORRECTION TAPE | F117: 24.00 | G117: 192 | H117: 196 | I117: =F117*G117 -> 4608 | J117: =F117*H117 -> 4704 | K117: =G117-H117 -> -4 | L117: =I117-J117 -> -96
B118: 20 | C118: OFFICE SUPPLIES | D118: 70091 | E118: PRINTING GATOR RUBBERBOND | F118: 20.00 | G118: 37 | H118: 37 | I118: =F118*G118 -> 740 | J118: =F118*H118 -> 740 | K118: =G118-H118 -> 0 | L118: =I118-J118 -> 0
B119: 20 | C119: OFFICE SUPPLIES | D119: 70092 | E119: PRINTING GOLDEN LION RUBBERBOND | F119: 4.50 | G119: 1 | H119: 1 | I119: =F119*G119 -> 4.5 | J119: =F119*H119 -> 4.5 | K119: =G119-H119 -> 0 | L119: =I119-J119 -> 0
B120: 20 | C120: OFFICE SUPPLIES | D120: 70283 | E120: PRINTING HBW MATRIX BLACK | F120: 6.00 | G120: =1490+11 -> 1501 | H120: 1501 | I120: =F120*G120 -> 9006 | J120: =F120*H120 -> 9006 | K120: =G120-H120 -> 0 | L120: =I120-J120 -> 0
B121: 20 | C121: OFFICE SUPPLIES | D121: 70093 | E121: PRINTING HBW STAMP PAD INK - RED | F121: 17.00 | G121: 9 | H121: 9 | I121: =F121*G121 -> 153 | J121: =F121*H121 -> 153 | K121: =G121-H121 -> 0 | L121: =I121-J121 -> 0
B122: 20 | C122: OFFICE SUPPLIES | D122: 70143 | E122: PRINTING HEAVY DUTY PUNCHER | F122: 150.00 | G122: 17 | H122: 17 | I122: =F122*G122 -> 2550 | J122: =F122*H122 -> 2550 | K122: =G122-H122 -> 0 | L122: =I122-J122 -> 0
B123: 20 | C123: OFFICE SUPPLIES | D123: 70198 | E123: PRINTING INTERMEDIATE PAD | F123: 18.00 | G123: 150 | H123: 150 | I123: =F123*G123 -> 2700 | J123: =F123*H123 -> 2700 | K123: =G123-H123 -> 0 | L123: =I123-J123 -> 0
B124: 20 | C124: OFFICE SUPPLIES | D124: 70260 | E124: PRINTING JACKET BURDA NAME ONLY | F124: 100.00 | G124: 1 | H124: 1 | I124: =F124*G124 -> 100 | J124: =F124*H124 -> 100 | K124: =G124-H124 -> 0 | L124: =I124-J124 -> 0
B125: 20 | C125: OFFICE SUPPLIES | D125: 70227 | E125: PRINTING JACKET BURDA ONLY-FRONT&BACK | F125: 200.00 | G125: 3 | H125: 3 | I125: =F125*G125 -> 600 | J125: =F125*H125 -> 600 | K125: =G125-H125 -> 0 | L125: =I125-J125 -> 0
B126: 20 | C126: OFFICE SUPPLIES | D126: 70094 | E126: PRINTING JOURNAL | F126: 21.00 | G126: 33 | H126: 33 | I126: =F126*G126 -> 693 | J126: =F126*H126 -> 693 | K126: =G126-H126 -> 0 | L126: =I126-J126 -> 0
B127: 20 | C127: OFFICE SUPPLIES | D127: 70095 | E127: PRINTING JOY CRAYONS BY 16 | F127: 14.00 | G127: 22 | H127: 22 | I127: =F127*G127 -> 308 | J127: =F127*H127 -> 308 | K127: =G127-H127 -> 0 | L127: =I127-J127 -> 0
B128: 20 | C128: OFFICE SUPPLIES | D128: 70098 | E128: PRINTING KODAK PHOTO PAPER A4 | F128: 115.00 | G128: 30 | H128: 30 | I128: =F128*G128 -> 3450 | J128: =F128*H128 -> 3450 | K128: =G128-H128 -> 0 | L128: =I128-J128 -> 0
B129: 20 | C129: OFFICE SUPPLIES | D129: 70229 | E129: PRINTING KOOPLYMPICS GRAY SHIRT | F129: 178.33 | G129: 10 | H129: 10 | I129: =F129*G129 -> 1783.3 | J129: =F129*H129 -> 1783.3 | K129: =G129-H129 -> 0 | L129: =I129-J129 -> 0
B130: 20 | C130: OFFICE SUPPLIES | D130: 70099 | E130: PRINTING KRISTAL TYPEWRITING PAPER LONG | F130: 27.00 | G130: 37 | H130: 37 | I130: =F130*G130 -> 999 | J130: =F130*H130 -> 999 | K130: =G130-H130 -> 0 | L130: =I130-J130 -> 0
B131: 20 | C131: OFFICE SUPPLIES | D131: 70100 | E131: PRINTING KRISTAL TYPEWRITING PAPER SHORT | F131: 22.50 | G131: 31 | H131: 31 | I131: =F131*G131 -> 697.5 | J131: =F131*H131 -> 697.5 | K131: =G131-H131 -> 0 | L131: =I131-J131 -> 0
B132: 20 | C132: OFFICE SUPPLIES | D132: 70259 | E132: PRINTING LAMINATE FILM LETTER SIZE 250MIC | F132: 15.00 | G132: 5 | H132: 5 | I132: =F132*G132 -> 75 | J132: =F132*H132 -> 75 | K132: =G132-H132 -> 0 | L132: =I132-J132 -> 0
... B158: 20 | C158: OFFICE SUPPLIES | D158: 70123 | E158: PRINTING PERFECT PRINT LONG | F158: 148.90 | G158: 206 | H158: 206 | I158: =F158*G158 -> 30673.4 | J158: =F158*H158 -> 30673.4 | K158: =G158-H158 -> 0 | L158: =I158-J158 -> 0
B159: 20 | C159: OFFICE SUPPLIES | D159: 70124 | E159: PRINTING PERFECT PRINT SHORT | F159: 126.00 | G159: =174+11 -> 185 | H159: 186 | I159: =F159*G159 -> 23310 | J159: =F159*H159 -> 23436 | K159: =G159-H159 -> -1 | L159: =I159-J159 -> -126
B160: 20 | C160: OFFICE SUPPLIES | D160: 70125 | E160: PRINTING PILOT BP-S-F FINE BALLPEN BLACK | F160: 17.75 | G160: 19 | H160: 19 | I160: =F160*G160 -> 337.25 | J160: =F160*H160 -> 337.25 | K160: =G160-H160 -> 0 | L160: =I160-J160 -> 0
B161: 20 | C161: OFFICE SUPPLIES | D161: 70127 | E161: PRINTING PILOT MARKER BLACK | F161: 35.75 | G161: 45 | H161: 45 | I161: =F161*G161 -> 1608.75 | J161: =F161*H161 -> 1608.75 | K161: =G161-H161 -> 0 | L161: =I161-J161 -> 0
B162: 20 | C162: OFFICE SUPPLIES | D162: 70128 | E162: PRINTING PILOT MARKER BLUE | F162: 27.00 | G162: 94 | H162: 94 | I162: =F162*G162 -> 2538 | J162: =F162*H162 -> 2538 | K162: =G162-H162 -> 0 | L162: =I162-J162 -> 0
B163: 20 | C163: OFFICE SUPPLIES | D163: 70129 | E163: PRINTING PILOT MARKER RED | F163: 27.00 | G163: 108 | H163: 108 | I163: =F163*G163 -> 2916 | J163: =F163*H163 -> 2916 | K163: =G163-H163 -> 0 | L163: =I163-J163 -> 0
B164: 20 | C164: OFFICE SUPPLIES | D164: 70130 | E164: PRINTING PILOT SUPER COLOR MARKER REFILL INK | F164: 100.00 | G164: 5 | H164: 5 | I164: =F164*G164 -> 500 | J164: =F164*H164 -> 500 | K164: =G164-H164 -> 0 | L164: =I164-J164 -> 0
B165: 20 | C165: OFFICE SUPPLIES | D165: 70131 | E165: PRINTING PILOT WYTEBOARD MARKER BLACK | F165: 55.25 | G165: 81 | H165: 81 | I165: =F165*G165 -> 4475.25 | J165: =F165*H165 -> 4475.25 | K165: =G165-H165 -> 0 | L165: =I165-J165 -> 0
B166: 20 | C166: OFFICE SUPPLIES | D166: 70132 | E166: PRINTING PILOT WYTEBOARD MARKER BLUE | F166: 43.40 | G166: 78 | H166: 78 | I166: =F166*G166 -> 3385.2 | J166: =F166*H166 -> 3385.2 | K166: =G166-H166 -> 0 | L166: =I166-J166 -> 0
B167: 20 | C167: OFFICE SUPPLIES | D167: 70133 | E167: PRINTING PILOT WYTEBOARD MARKER RED | F167: 43.40 | G167: 70 | H167: 70 | I167: =F167*G167 -> 3038 | J167: =F167*H167 -> 3038 | K167: =G167-H167 -> 0 | L167: =I167-J167 -> 0
B168: 20 | C168: OFFICE SUPPLIES | D168: 70172 | E168: PRINTING PLASTIC CASE OF CALLING CARDS | F168: 5.00 | G168: 46 | H168: 46 | I168: =F168*G168 -> 230 | J168: =F168*H168 -> 230 | K168: =G168-H168 -> 0 | L168: =I168-J168 -> 0
B169: 20 | C169: OFFICE SUPPLIES | D169: 70134 | E169: PRINTING PLASTIC ENVELOPE SHORT | F169: 6.00 | G169: 159 | H169: 159 | I169: =F169*G169 -> 954 | J169: =F169*H169 -> 954 | K169: =G169-H169 -> 0 | L169: =I169-J169 -> 0
B170: 20 | C170: OFFICE SUPPLIES | D170: 70246 | E170: PRINTING PLASTIC FOLDER GREEN LONG | F170: 12.00 | G170: 20 | H170: 20 | I170: =F170*G170 -> 240 | J170: =F170*H170 -> 240 | K170: =G170-H170 -> 0 | L170: =I170-J170 -> 0
B171: 20 | C171: OFFICE SUPPLIES | D171: 70321 | E171: PRINTING PLASTIC FOLDER GREEN LONG - 3 | F171: 13.00 | G171: 180 | H171: 180 | I171: =F171*G171 -> 2340 | J171: =F171*H171 -> 2340 | K171: =G171-H171 -> 0 | L171: =I171-J171 -> 0
... B185: 20 | C185: OFFICE SUPPLIES | D185: 70145 | E185: PRINTING SCISSOR | F185: 16.50 | G185: 1 | H185: 1 | I185: =F185*G185 -> 16.5 | J185: =F185*H185 -> 16.5 | K185: =G185-H185 -> 0 | L185: =I185-J185 -> 0
B186: 20 | C186: OFFICE SUPPLIES | D186: 70315 | E186: PRINTING SCISSOR - 2 | F186: 115.00 | G186: 22 | H186: 22 | I186: =F186*G186 -> 2530 | J186: =F186*H186 -> 2530 | K186: =G186-H186 -> 0 | L186: =I186-J186 -> 0
B187: 20 | C187: OFFICE SUPPLIES | D187: 70305 | E187: PRINTING SCOTCH TAPE 1- 2 | F187: 12.00 | G187: 65 | H187: 65 | I187: =F187*G187 -> 780 | J187: =F187*H187 -> 780 | K187: =G187-H187 -> 0 | L187: =I187-J187 -> 0
B188: 20 | C188: OFFICE SUPPLIES | D188: 70271 | E188: PRINTING SHINY RECORD BOOK 150 PAGES | F188: 52.00 | G188: 38 | H188: 38 | I188: =F188*G188 -> 1976 | J188: =F188*H188 -> 1976 | K188: =G188-H188 -> 0 | L188: =I188-J188 -> 0
B189: 20 | C189: OFFICE SUPPLIES | D189: 70273 | E189: PRINTING SHINY RECORD BOOK 500 PAGES | F189: 95.00 | G189: 23 | H189: 23 | I189: =F189*G189 -> 2185 | J189: =F189*H189 -> 2185 | K189: =G189-H189 -> 0 | L189: =I189-J189 -> 0
B190: 20 | C190: OFFICE SUPPLIES | D190: 70196 | E190: PRINTING SOFTCARD ID HOLDER | F190: 7.00 | G190: 123 | H190: 123 | I190: =F190*G190 -> 861 | J190: =F190*H190 -> 861 | K190: =G190-H190 -> 0 | L190: =I190-J190 -> 0
B191: 20 | C191: OFFICE SUPPLIES | D191: 70149 | E191: PRINTING SPIRAL WRITING NOTEBOOK | F191: 8.50 | G191: 5 | H191: 5 | I191: =F191*G191 -> 42.5 | J191: =F191*H191 -> 42.5 | K191: =G191-H191 -> 0 | L191: =I191-J191 -> 0
B192: 20 | C192: OFFICE SUPPLIES | D192: 70191 | E192: PRINTING STABILO BOSS HIGHLIGHTER | F192: 38.50 | G192: 42 | H192: 42 | I192: =F192*G192 -> 1617 | J192: =F192*H192 -> 1617 | K192: =G192-H192 -> 0 | L192: =I192-J192 -> 0
B193: 20 | C193: OFFICE SUPPLIES | D193: 70150 | E193: PRINTING STAINLESS FASTENER | F193: 88.00 | G193: 10 | H193: 10 | I193: =F193*G193 -> 880 | J193: =F193*H193 -> 880 | K193: =G193-H193 -> 0 | L193: =I193-J193 -> 0
B194: 20 | C194: OFFICE SUPPLIES | D194: 70004 | E194: PRINTING STAMP PAD INK PURPLE | F194: 17.00 | G194: 11 | H194: 11 | I194: =F194*G194 -> 187 | J194: =F194*H194 -> 187 | K194: =G194-H194 -> 0 | L194: =I194-J194 -> 0
B195: 20 | C195: OFFICE SUPPLIES | D195: 70151 | E195: PRINTING STAMP PAD NO. 3 VIOLET INK | F195: 20.00 | G195: 6 | H195: 6 | I195: =F195*G195 -> 120 | J195: =F195*H195 -> 120 | K195: =G195-H195 -> 0 | L195: =I195-J195 -> 0
B196: 20 | C196: OFFICE SUPPLIES | D196: 70153 | E196: PRINTING STAPLE WIRE #35 MAX | F196: 65.00 | G196: 15 | H196: 15 | I196: =F196*G196 -> 975 | J196: =F196*H196 -> 975 | K196: =G196-H196 -> 0 | L196: =I196-J196 -> 0
B197: 20 | C197: OFFICE SUPPLIES | D197: 70295 | E197: PRINTING STAPLE WIRE #35 MAX - 2 | F197: 75.00 | G197: 71 | H197: 71 | I197: =F197*G197 -> 5325 | J197: =F197*H197 -> 5325 | K197: =G197-H197 -> 0 | L197: =I197-J197 -> 0
B198: 20 | C198: OFFICE SUPPLIES | D198: 70154 | E198: PRINTING STAPLER HD-50R/ML | F198: 450.00 | G198: 1 | H198: 1 | I198: =F198*G198 -> 450 | J198: =F198*H198 -> 450 | K198: =G198-H198 -> 0 | L198: =I198-J198 -> 0
... B225: 20 | C225: OFFICE SUPPLIES | D225: 70199 | E225: PRINTING YELLOW RULED PAD | F225: 26.00 | G225: 49 | H225: 49 | I225: =F225*G225 -> 1274 | J225: =F225*H225 -> 1274 | K225: =G225-H225 -> 0 | L225: =I225-J225 -> 0
B226: TOTAL | G226: =SUM(G6:G225) -> 2266 | H226: =SUM(H6:H225) -> 35452 | I226: =SUM(I6:I225) -> 453533.1 | J226: =SUM(J6:J225) -> 457363.15 | K226: =SUM(K6:K225) -> -843 | L226: =SUM(L6:L225) -> -3830.05
B228: PARTICULARS | D228: TOTAL COST | E228: TOTAL QUANTITY | F228: ACTION PLAN ON THE DEVIATION
B229: RECORD | D229: =I226 -> 453533.1 | E229: =G226 -> 2266 | F229: Overage will be adjusted to the system while shortage will be charged to the accountable staff.
B230: ACTUAL INVENTORY | D230: =J226 -> 457363.15 | E230: =H226 -> 35452
B231: VARIANCE | D231: =D229-D230 -> -3830.05 | E231: =E229-E230 -> -33186
B233: PREPARED BY: | E233: CHECKED BY: | H233: COMFORMED BY:
B235: =#REF! -> #REF! | E235: NERISSA C. DULDULAO / TERESITA B. OLAR | H235: MICHAEL PASCUA
B236: INVENTORY CONTROLLER | E236: ACCOUNTANT / ACCOUNTING SUPERVISOR | H236: OPERATION - UNIT HEAD
B239: RECOMMENDING APPROVAL BY: | H239: APPROVED BY:
B241: KATHERINE DC. SANTOS | H241: JASPER D. SANTOS
...

Sheet VB-3
A1: VARIANCE BREAKDOWN (PRINTING)
A2: =PRINTING!B2 -> AS OF JUNE 2026
B3: OVER
B4: BARCODE | C4: PRODUCT NAME | D4: UNIT COST | E4: QUANTITY PER RECORD / ACCPOS | F4: ACTUAL INVENTORY | G4: JAN. ACTUAL | H4: REMARKS | I4: VARIANCE - QUANTITY | J4: VARIANCE - COST | K4: REMARKS / CAUSE OF VARIANCE
B5: 70016 | C5: PRINTING BONUS LONG | D5: 99.30 | E5: 99 | F5: 109 | G5: 9830.7 | H5: 10823.7 | I5: -10 | J5: -993
B6: 70017 | C6: PRINTING BONUS SHORT | D6: 84.00 | E6: 116 | F6: 123 | G6: 9744 | H6: 10332 | I6: -7 | J6: -588
B7: 70170 | C7: PRINTING CLIENTS ID | D7: 1.50 | E7: 3650 | F7: 4000 | G7: 5475 | H7: 6000 | I7: -350 | J7: -525
B8: 70054 | C8: PRINTING DOUBLE SIDED TAPE | D8: 28.00 | E8: 20 | F8: 21 | G8: 560 | H8: 588 | I8: -1 | J8: -28
B9: 70085 | C9: PRINTING FOLDER LONG WHITE | D9: 2.70 | E9: 2294 | F9: 2760 | G9: 6193.8 | H9: 7452 | I9: -466 | J9: -1258.2
B10: 70173 | C10: PRINTING FORMS BONUS LONG | D10: 115.85 | E10: 20 | F10: 21 | G10: 2317 | H10: 2432.85 | I10: -1 | J10: -115.85
B11: 70306 | C11: PRINTING GATOR CORRECTION TAPE | D11: 24.00 | E11: 192 | F11: 196 | G11: 4608 | H11: 4704 | I11: -4 | J11: -96
B12: 70124 | C12: PRINTING PERFECT PRINT SHORT | D12: 126.00 | E12: 185 | F12: 186 | G12: 23310 | H12: 23436 | I12: -1 | J12: -126
B13: 70168 | C13: PRINTING WORX BONDPAPER LONG | D13: 32.00 | E13: 18 | F13: 19 | G13: 576 | H13: 608 | I13: -1 | J13: -32
B14: 70169 | C14: PRINTING WORX BONDPAPER SHORT | D14: 34.00 | E14: 92 | F14: 94 | G14: 3128 | H14: 3196 | I14: -2 | J14: -68
I42: =SUM(I5:I41) -> -843 | J42: =SUM(J5:J41) -> -3830.05
B44: RETURN
B45: BARCODE | C45: PRODUCT NAME | D45: UNIT COST | G45: VARIANCE - QUANTITY | H45: VARIANCE - COST | I45: REMARKS / CAUSE OF VARIANCE
H46: =D46*G46 -> 0
G47: =SUM(G46:G46) -> 0 | H47: =SUM(H46:H46) -> 0 | I47: =SUM(I46:I46) -> 0
B48: SHORT
B49: BARCODE | C49: PRODUCT NAME | D49: UNIT COST | E49: QUANTITY PER RECORD / ACCPOS | F49: ACTUAL INVENTORY | G49: JAN. ACTUAL | H49: REMARKS | I49: VARIANCE - QUANTITY | J49: VARIANCE - COST | K49: REMARKS / CAUSE OF VARIANCE
I75: =SUM(I50:I74) -> 0 | J75: =SUM(J50:J74) -> 0
B79: SHORT
B80: BARCODE | C80: PRODUCT NAME | D80: SRP | E80: QUANTITY PER RECORD / ACCPOS | F80: ACTUAL INVENTORY | G80: TOTAL COST - RECORD | H80: TOTAL COST - ACTUAL INVENTORY | I80: VARIANCE - QUANTITY | J80: VARIANCE - COST | K80: REMARKS / CAUSE OF VARIANCE
I84: =SUM(I81:I83) -> 0 | J84: =SUM(J81:J83) -> 0

Sheet CONVIE - final
B1: INVENTORY REPORT
B2: =PRINTING!B2 -> AS OF JUNE 2026
B3: COOP STORE
U4: STORE | W4: BODEGA 1 | Y4: BODEGA 2 | AA4: BO - COUNTER | AD4: EXPIRED
B5: SHELF NO. | C5: SHELF DESCRIPTION | D5: BARCODE | E5: PRODUCT NAME | F5: UNIT COST | G5: Actual Count May 2026 | H5: KINALANGUYAN STORE/Adjustment | I5: PURCHASES/ RETAIL | J5: PULL OUT | K5: SALES | L5: TOTAL | M5: ACTUAL INVENTORY | N5: TOTAL COST - RECORD | O5: TOTAL COST - ACTUAL INVENTORY | P5: VARIANCE - QUANTITY | Q5: VARIANCE - COST | R5: REMARKS / CAUSE OF VARIANCE | U5: QTY | V5: REMARKS | W5: QTY | X5: REMARKS | Y5: QTY | Z5: REMARKS | AA5: QTY | AB5: REMARKS | AD5: QTY | AE5: AMOUNT
B6: 1 | C6: CHIPS & SNACK | D6: 4800631001928 | E6: BOY BAWANG ASSORTED NUTS 85G | F6: 18.53 | G6: 11 | H6: 20 | K6: 30 | L6: =G6+I6-J6-K6+H6 -> 1 | M6: 1 | N6: =F6*L6 -> 18.53 | O6: =M6*F6 -> 18.53 | P6: =L6-M6 -> 0 | Q6: =N6-O6 -> 0 | S6: =U6+Y6+W6+AA6 -> 5 | T6: =M6-S6 -> -4 | U6: 5
B7: 1 | C7: CHIPS & SNACK | D7: 4809011 681392 | E7: BOY BAWANG CHILI CHEESE 100G | F7: 16.03 | G7: 23 | K7: 8 | L7: =G7+I7-J7-K7+H7 -> 15 | M7: 15 | N7: =F7*L7 -> 240.45 | O7: =M7*F7 -> 240.45 | P7: =L7-M7 -> 0 | Q7: =N7-O7 -> 0 | S7: =U7+Y7+W7+AA7 -> 26 | T7: =M7-S7 -> -11 | U7: 26
B8: 1 | C8: CHIPS & SNACK | D8: 4809011681095 | E8: BOY BAWANG CORNICK ADOBO 100G | F8: 16.03 | G8: 17 | K8: 4 | L8: =G8+I8-J8-K8+H8 -> 13 | M8: =10+2 -> 12 | N8: =F8*L8 -> 208.39 | O8: =M8*F8 -> 192.36 | P8: =L8-M8 -> 1 | Q8: =N8-O8 -> 16.03 | S8: =U8+Y8+W8+AA8 -> 23 | T8: =M8-S8 -> -11 | U8: 23
B9: 1 | C9: CHIPS & SNACK | D9: 4809011681507 | E9: BOY BAWANG CORNICK BBQ FLAVOR 100G | F9: 16.03 | G9: 70 | K9: 4 | L9: =G9+I9-J9-K9+H9 -> 66 | M9: =28+37 -> 65 | N9: =F9*L9 -> 1057.98 | O9: =M9*F9 -> 1041.95 | P9: =L9-M9 -> 1 | Q9: =N9-O9 -> 16.03 | S9: =U9+Y9+W9+AA9 -> 33 | T9: =M9-S9 -> 32 | U9: 33
B10: 1 | C10: CHIPS & SNACK | D10: 4800631681311 | E10: BOY BAWANG CORNICK LECHON MANOK FLAVOR | F10: 16.03 | G10: 25 | K10: 1 | L10: =G10+I10-J10-K10+H10 -> 24 | M10: =23+1 -> 24 | N10: =F10*L10 -> 384.72 | O10: =M10*F10 -> 384.72 | P10: =L10-M10 -> 0 | Q10: =N10-O10 -> 0 | S10: =U10+Y10+W10+AA10 -> 27 | T10: =M10-S10 -> -3 | U10: 27
B11: 1 | C11: CHIPS & SNACK | D11: 4800631000419 | E11: BOY BAWANG CRACKER NUTS 85G | F11: 17.95 | G11: 3 | K11: 3 | L11: =G11+I11-J11-K11+H11 -> 0 | N11: =F11*L11 -> 0 | O11: =M11*F11 -> 0 | P11: =L11-M11 -> 0 | Q11: =N11-O11 -> 0 | R11: over 3 sales | S11: =U11+Y11+W11+AA11 -> 5 | T11: =M11-S11 -> -5 | U11: 5
B12: 1 | C12: CHIPS & SNACK | D12: 4809011681378 | E12: BOY BAWANG GARLIC FLAVOR 100G | F12: 16.03 | G12: 58 | K12: 2 | L12: =G12+I12-J12-K12+H12 -> 56 | M12: 56 | N12: =F12*L12 -> 897.68 | O12: =M12*F12 -> 897.68 | P12: =L12-M12 -> 0 | Q12: =N12-O12 -> 0 | S12: =U12+Y12+W12+AA12 -> 19 | T12: =M12-S12 -> 37 | U12: 19
B13: 1 | C13: CHIPS & SNACK | D13: 4809011681194 | E13: BOY BAWANG HOT GARLIC 100G | F13: 16.03 | G13: 0 | L13: =G13+I13-J13-K13+H13 -> 0 | N13: =F13*L13 -> 0 | O13: =M13*F13 -> 0 | P13: =L13-M13 -> 0 | Q13: =N13-O13 -> 0 | S13: =U13+Y13+W13+AA13 -> 0 | T13: =M13-S13 -> 0
B14: 1 | C14: CHIPS & SNACK | D14: 4800631000488 | E14: BOY BAWANG MIXED NUTS GARLIC FLAVOR 100G | F14: 32.13 | G14: 36 | K14: 6 | L14: =G14+I14-J14-K14+H14 -> 30 | M14: 30 | N14: =F14*L14 -> 963.9 | O14: =M14*F14 -> 963.9 | P14: =L14-M14 -> 0 | Q14: =N14-O14 -> 0 | R14: 1-Expired 4/15/2025 | S14: =U14+Y14+W14+AA14 -> 4 | T14: =M14-S14 -> 26 | U14: 4
B15: 1 | C15: CHIPS & SNACK | D15: 4800631001867 | E15: BOY BAWANG SNACK MIX W/ REAL GARLIC CHIPS 85G | F15: 18.53 | G15: 19 | K15: 7 | L15: =G15+I15-J15-K15+H15 -> 12 | M15: 12 | N15: =F15*L15 -> 222.36 | O15: =M15*F15 -> 222.36 | P15: =L15-M15 -> 0 | Q15: =N15-O15 -> 0 | S15: =U15+Y15+W15+AA15 -> 27 | T15: =M15-S15 -> -15 | U15: 27
B16: 1 | C16: CHIPS & SNACK | D16: 4800194104128 | E16: CHEEZ ON CHIPS CHEESE FLAVOR 22G | F16: 6.18 | G16: 92 | K16: 1 | L16: =G16+I16-J16-K16+H16 -> 91 | M16: 91 | N16: =F16*L16 -> 562.38 | O16: =M16*F16 -> 562.38 | P16: =L16-M16 -> 0 | Q16: =N16-O16 -> 0 | R16: over 1 sales | S16: =U16+Y16+W16+AA16 -> 94 | T16: =M16-S16 -> -3 | U16: 6 | W16: =37+50+1 -> 88 | X16: EXPIRED 2024 MAY 2026-50 | AD16: 50 | AE16: =AD16*F16 -> 309
B17: 1 | C17: CHIPS & SNACK | D17: 4800216125919 | E17: CHEEZY CORN CRUNCH CHEESE 150G | F17: 51.54 | G17: 1 | L17: =G17+I17-J17-K17+H17 -> 1 | M17: 1 | N17: =F17*L17 -> 51.54 | O17: =M17*F17 -> 51.54 | P17: =L17-M17 -> 0 | Q17: =N17-O17 -> 0 | S17: =U17+Y17+W17+AA17 -> 1 | T17: =M17-S17 -> 0 | U17: 1
B18: 1 | C18: CHIPS & SNACK | D18: 4800216121041 | E18: CHEEZY CORN CRUNCH CHEESE 24G | F18: 7.4 | G18: 10 | L18: =G18+I18-J18-K18+H18 -> 10 | M18: 10 | N18: =F18*L18 -> 74 | O18: =M18*F18 -> 74 | P18: =L18-M18 -> 0 | Q18: =N18-O18 -> 0 | S18: =U18+Y18+W18+AA18 -> 10 | T18: =M18-S18 -> 0 | U18: 10
B19: 1 | C19: CHIPS & SNACK | D19: 4800216121058 | E19: CHEEZY CORN CRUNCH CHEESE 70G | F19: 26.09 | G19: 19 | K19: 2 | L19: =G19+I19-J19-K19+H19 -> 17 | M19: 17 | N19: =F19*L19 -> 443.53 | O19: =M19*F19 -> 443.53 | P19: =L19-M19 -> 0 | Q19: =N19-O19 -> 0 | S19: =U19+Y19+W19+AA19 -> 23 | T19: =M19-S19 -> -6 | U19: 23
B20: 1 | C20: CHIPS & SNACK | D20: 4800216121911 | E20: CHEEZY CORN CRUNCH RED HOT 22G | F20: 7.4 | L20: =G20+I20-J20-K20+H20 -> 0 | N20: =F20*L20 -> 0 | O20: =M20*F20 -> 0 | P20: =L20-M20 -> 0 | Q20: =N20-O20 -> 0 | S20: =U20+Y20+W20+AA20 -> 0 | T20: =M20-S20 -> 0
B21: 1 | C21: CHIPS & SNACK | D21: 4800216122437 | E21: CHEEZY CORN CRUNCH RED HOT 70G | F21: 26.09 | G21: 11 | K21: 1 | L21: =G21+I21-J21-K21+H21 -> 10 | M21: 10 | N21: =F21*L21 -> 260.9 | O21: =M21*F21 -> 260.9 | P21: =L21-M21 -> 0 | Q21: =N21-O21 -> 0 | S21: =U21+Y21+W21+AA21 -> 12 | T21: =M21-S21 -> -2 | U21: 12
B22: 1 | C22: CHIPS & SNACK | D22: 4800016115424 | E22: CHICHARRON NI MANG JUAN KLASIK CHICHARON 90G | F22: 17.1 | L22: =G22+I22-J22-K22+H22 -> 0 | N22: =F22*L22 -> 0 | O22: =M22*F22 -> 0 | P22: =L22-M22 -> 0 | Q22: =N22-O22 -> 0 | S22: =U22+Y22+W22+AA22 -> 0 | T22: =M22-S22 -> 0
B23: 1 | C23: CHIPS & SNACK | D23: 4800016110535 | E23: CHICHARRON NI MANG JUAN PAOMBONG 26G | F23: 6.83 | G23: 31 | H23: 20 | K23: 22 | L23: =G23+I23-J23-K23+H23 -> 29 | M23: 28 | N23: =F23*L23 -> 198.07 | O23: =M23*F23 -> 191.24 | P23: =L23-M23 -> 1 | Q23: =N23-O23 -> 6.83 | S23: =U23+Y23+W23+AA23 -> 35 | T23: =M23-S23 -> -7 | U23: 35
B24: 1 | C24: CHIPS & SNACK | D24: 4800016110511 | E24: CHICHARRON NI MANG JUAN PAOMBONG 90G | F24: 19.4 | L24: =G24+I24-J24-K24+H24 -> 0 | N24: =F24*L24 -> 0 | O24: =M24*F24 -> 0 | P24: =L24-M24 -> 0 | Q24: =N24-O24 -> 0 | S24: =U24+Y24+W24+AA24 -> 0 | T24: =M24-S24 -> 0
B25: 1 | C25: CHIPS & SNACK | D25: 4800016110542 | E25: CHICHARRON NI MANG JUAN SUKAT SILI 26G | F25: 6.83 | G25: 33 | K25: 3 | L25: =G25+I25-J25-K25+H25 -> 30 | M25: 29 | N25: =F25*L25 -> 204.9 | O25: =M25*F25 -> 198.07 | P25: =L25-M25 -> 1 | Q25: =N25-O25 -> 6.83 | S25: =U25+Y25+W25+AA25 -> 36 | T25: =M25-S25 -> -7 | U25: 36
B26: 1 | C26: CHIPS & SNACK | D26: 4800016110528 | E26: CHICHARRON NI MANG JUAN SUKAT SILI 90G | F26: 19.4 | L26: =G26+I26-J26-K26+H26 -> 0 | N26: =F26*L26 -> 0 | O26: =M26*F26 -> 0 | P26: =L26-M26 -> 0 | Q26: =N26-O26 -> 0 | S26: =U26+Y26+W26+AA26 -> 0 | T26: =M26-S26 -> 0
B27: 1 | C27: CHIPS & SNACK | D27: 4806505854423 | E27: CHICK BOY CALIFORNIA CRUNCH ONION & GARLIC FLAVOR 100G | F27: 17.65 | G27: 2 | H27: 10 | K27: 10 | L27: =G27+I27-J27-K27+H27 -> 2 | M27: 2 | N27: =F27*L27 -> 35.3 | O27: =M27*F27 -> 35.3 | P27: =L27-M27 -> 0 | Q27: =N27-O27 -> 0 | S27: =U27+Y27+W27+AA27 -> 6 | T27: =M27-S27 -> -4 | U27: 6
B28: 1 | C28: CHIPS & SNACK | D28: 4806505854225 | E28: CHICK BOY CHEESE FLAVOR 100G | F28: 17.65 | G28: 9 | K28: 1 | L28: =G28+I28-J28-K28+H28 -> 8 | M28: 8 | N28: =F28*L28 -> 141.2 | O28: =M28*F28 -> 141.2 | P28: =L28-M28 -> 0 | Q28: =N28-O28 -> 0 | S28: =U28+Y28+W28+AA28 -> 10 | T28: =M28-S28 -> -2 | U28: 10
B29: 1 | C29: CHIPS & SNACK | D29: 4806505854232 | E29: CHICK BOY SWEET CORN FLAVOR 100G | F29: 17.65 | G29: 15 | H29: 10 | K29: 19 | L29: =G29+I29-J29-K29+H29 -> 6 | M29: 6 | N29: =F29*L29 -> 105.9 | O29: =M29*F29 -> 105.9 | P29: =L29-M29 -> 0 | Q29: =N29-O29 -> 0 | S29: =U29+Y29+W29+AA29 -> 1 | T29: =M29-S29 -> 5 | U29: 1
B30: 1 | C30: CHIPS & SNACK | D30: 4806505854416 | E30: CHICK BOY TEXAS SMOKED BBQ FLAVOR 100G | F30: 17.65 | G30: 2 | H30: 10 | K30: 12 | L30: =G30+I30-J30-K30+H30 -> 0 | N30: =F30*L30 -> 0 | O30: =M30*F30 -> 0 | P30: =L30-M30 -> 0 | Q30: =N30-O30 -> 0 | S30: =U30+Y30+W30+AA30 -> 1 | T30: =M30-S30 -> -1 | U30: 1
B31: 1 | C31: CHIPS & SNACK | D31: 4800016115011 | E31: CHICKN SKIN NI MANG JUAN 17G | F31: 7.06 | H31: 35 | L31: =G31+I31-J31-K31+H31 -> 35 | M31: 35 | N31: =F31*L31 -> 247.1 | O31: =M31*F31 -> 247.1 | P31: =L31-M31 -> 0 | Q31: =N31-O31 -> 0 | S31: =U31+Y31+W31+AA31 -> 0 | T31: =M31-S31 -> 35
B32: 1 | C32: CHIPS & SNACK | D32: 4800016115011 | E32: CHICKN SKIN NI MANG JUAN 17G | F32: 7.056 | I32: 100 | K32: 40 | L32: =G32+I32-J32-K32+H32 -> 60 | M32: 60 | N32: =F32*L32 -> 423.36 | O32: =M32*F32 -> 423.36 | P32: =L32-M32 -> 0 | Q32: =N32-O32 -> 0 | S32: =U32+Y32+W32+AA32 -> 0 | T32: =M32-S32 -> 60
B33: 1 | C33: CHIPS & SNACK | D33: 4800016115257 | E33: CHICKN SKIN NI MANG JUAN 70G | F33: 18.03 | G33: 27 | J33: 27 | L33: =G33+I33-J33-K33+H33 -> 0 | N33: =F33*L33 -> 0 | O33: =M33*F33 -> 0 | P33: =L33-M33 -> 0 | Q33: =N33-O33 -> 0 | S33: =U33+Y33+W33+AA33 -> 28 | T33: =M33-S33 -> -28 | U33: 28
B34: 1 | C34: CHIPS & SNACK | D34: 4800016643095 | E34: CHIPPY BBQ FLAVOR 110G | F34: 22.68 | G34: 16 | K34: 3 | L34: =G34+I34-J34-K34+H34 -> 13 | M34: 13 | N34: =F34*L34 -> 294.84 | O34: =M34*F34 -> 294.84 | P34: =L34-M34 -> 0 | Q34: =N34-O34 -> 0 | S34: =U34+Y34+W34+AA34 -> 23 | T34: =M34-S34 -> -10 | U34: 23
B35: 1 | C35: CHIPS & SNACK | D35: 4800016643095 | E35: CHIPPY BBQ FLAVOR 110G | F35: 23.07 | L35: =G35+I35-J35-K35+H35 -> 0 | N35: =F35*L35 -> 0 | O35: =M35*F35 -> 0 | P35: =L35-M35 -> 0 | Q35: =N35-O35 -> 0 | S35: =U35+Y35+W35+AA35 -> 0 | T35: =M35-S35 -> 0
B36: 1 | C36: CHIPS & SNACK | D36: 4800016642029 | E36: CHIPPY BBQ FLAVOR 27G | F36: 6.71 | G36: 3 | H36: 1 | J36: 1 | K36: 2 | L36: =G36+I36-J36-K36+H36 -> 1 | M36: 1 | N36: =F36*L36 -> 6.71 | O36: =M36*F36 -> 6.71 | P36: =L36-M36 -> 0 | Q36: =N36-O36 -> 0 | S36: =U36+Y36+W36+AA36 -> 7 | T36: =M36-S36 -> -6 | U36: 7
B37: 1 | C37: CHIPS & SNACK | D37: 4800016642029 | E37: CHIPPY BBQ FLAVOR 27G | F37: 6.83 | L37: =G37+I37-J37-K37+H37 -> 0 | N37: =F37*L37 -> 0 | O37: =M37*F37 -> 0 | P37: =L37-M37 -> 0 | Q37: =N37-O37 -> 0 | S37: =U37+Y37+W37+AA37 -> 0 | T37: =M37-S37 -> 0
B38: 1 | C38: CHIPS & SNACK | D38: 4800194117326 | E38: CHOCO FLAKES CEREALS 22G | F38: 6.18 | G38: 141 | L38: =G38+I38-J38-K38+H38 -> 141 | M38: =57+50+34 -> 141 | N38: =F38*L38 -> 871.38 | O38: =M38*F38 -> 871.38 | P38: =L38-M38 -> 0 | Q38: =N38-O38 -> 0 | R38: 46143 | S38: =U38+Y38+W38+AA38 -> 141 | T38: =M38-S38 -> 0 | U38: 34 | W38: =57+50 -> 107 | X38: EXPIRED 2024 & MAY 2026-50 | AD38: 57 | AE38: =AD38*F38 -> 352.26
B39: 1 | C39: CHIPS & SNACK | D39: 4800216110045 | E39: CLOVER CHEESE 145G | F39: 51.06 | G39: 24 | H39: 1 | L39: =G39+I39-J39-K39+H39 -> 25 | M39: 25 | N39: =F39*L39 -> 1276.5 | O39: =M39*F39 -> 1276.5 | P39: =L39-M39 -> 0 | Q39: =N39-O39 -> 0 | R39: 45343 | S39: =U39+Y39+W39+AA39 -> 25 | T39: =M39-S39 -> 0 | W39: 25 | X39: EXPIRED 2024 | AD39: =W39 -> 25 | AE39: =AD39*F39 -> 1276.5
B40: 1 | C40: CHIPS & SNACK | D40: 4800216120013 | E40: CLOVER CHEESE 24G | F40: 7.51 | G40: 94 | K40: 8 | L40: =G40+I40-J40-K40+H40 -> 86 | M40: =64+20 -> 84 | N40: =F40*L40 -> 645.86 | O40: =M40*F40 -> 630.84 | P40: =L40-M40 -> 2 | Q40: =N40-O40 -> 15.02 | R40: 20-EXPIRED 8/21/2024 | S40: =U40+Y40+W40+AA40 -> 99 | T40: =M40-S40 -> -15 | U40: 79 | W40: 20 | X40: EXPIRED 2024 | AD40: =W40 -> 20 | AE40: =AD40*F40 -> 150.2
B41: 1 | C41: CHIPS & SNACK | D41: 4800216110069 | E41: CLOVER CHIPS CHEESE 55G | F41: 22.19 | G41: 3 | H41: 5 | K41: 5 | L41: =G41+I41-J41-K41+H41 -> 3 | N41: =F41*L41 -> 66.57 | O41: =M41*F41 -> 0 | P41: =L41-M41 -> 3 | Q41: =N41-O41 -> 66.57 | S41: =U41+Y41+W41+AA41 -> 3 | T41: =M41-S41 -> -3 | W41: 3 | X41: EXPIRED 2025 | AD41: =W41 -> 3 | AE41: =AD41*F41 -> 66.57
B42: 1 | C42: CHIPS & SNACK | D42: 4800216110014 | E42: CLOVER CHIPS CHEESE 85G | F42: 31.96 | L42: =G42+I42-J42-K42+H42 -> 0 | N42: =F42*L42 -> 0 | O42: =M42*F42 -> 0 | P42: =L42-M42 -> 0 | Q42: =N42-O42 -> 0 | S42: =U42+Y42+W42+AA42 -> 0 | T42: =M42-S42 -> 0
B43: 1 | C43: CHIPS & SNACK | D43: 4800216126800 | E43: CLOVER CHIPS CHILI&CHEESE 55G | F43: 21.34 | G43: 7 | L43: =G43+I43-J43-K43+H43 -> 7 | M43: 7 | N43: =F43*L43 -> 149.38 | O43: =M43*F43 -> 149.38 | P43: =L43-M43 -> 0 | Q43: =N43-O43 -> 0 | R43: 45903 | S43: =U43+Y43+W43+AA43 -> 7 | T43: =M43-S43 -> 0 | W43: 5 | X43: EXPIRED 2025 | AA43: 2 | AB43: EXPIRED AUG 2025 | AD43: =AA43+W43 -> 7 | AE43: =AD43*F43 -> 149.38
B44: 1 | C44: CHIPS & SNACK | D44: 4800194116114 | E44: CORN OLE BARBECUE FLAVOR 22G | F44: 6.18 | G44: 77 | L44: =G44+I44-J44-K44+H44 -> 77 | M44: =50+23 -> 73 | N44: =F44*L44 -> 475.86 | O44: =M44*F44 -> 451.14 | P44: =L44-M44 -> 4 | Q44: =N44-O44 -> 24.72 | S44: =U44+Y44+W44+AA44 -> 77 | T44: =M44-S44 -> -4 | U44: 27 | W44: 50
B45: 1 | C45: CHIPS & SNACK | D45: 4800092772214 | E45: CRISS CROSS CREAMY CHEESE 20G | F45: 5.66 | L45: =G45+I45-J45-K45+H45 -> 0 | N45: =F45*L45 -> 0 | O45: =M45*F45 -> 0 | P45: =L45-M45 -> 0 | Q45: =N45-O45 -> 0 | S45: =U45+Y45+W45+AA45 -> 0 | T45: =M45-S45 -> 0
B46: 1 | C46: CHIPS & SNACK | D46: 4800092331909 | E46: DING DONG MIXED NUTS HOT N SPICY 100G | F46: 19.08 | L46: =G46+I46-J46-K46+H46 -> 0 | N46: =F46*L46 -> 0 | O46: =M46*F46 -> 0 | P46: =L46-M46 -> 0 | Q46: =N46-O46 -> 0 | S46: =U46+Y46+W46+AA46 -> 0 | T46: =M46-S46 -> 0
B47: 1 | C47: CHIPS & SNACK | D47: 4800092330131 | E47: DING DONG MIXED NUTS PLAIN 100G | F47: 19.08 | L47: =G47+I47-J47-K47+H47 -> 0 | N47: =F47*L47 -> 0 | O47: =M47*F47 -> 0 | P47: =L47-M47 -> 0 | Q47: =N47-O47 -> 0 | S47: =U47+Y47+W47+AA47 -> 0 | T47: =M47-S47 -> 0
B48: 1 | C48: CHIPS & SNACK | D48: 4800092333057 | E48: DRAGON SID PREMIUM SQUASH SEEDS 20G | F48: 5.89 | L48: =G48+I48-J48-K48+H48 -> 0 | N48: =F48*L48 -> 0 | O48: =M48*F48 -> 0 | P48: =L48-M48 -> 0 | Q48: =N48-O48 -> 0 | S48: =U48+Y48+W48+AA48 -> 0 | T48: =M48-S48 -> 0
B49: 1 | C49: CHIPS & SNACK | D49: 4800092771187 | E49: FUNKY FRENCH FRY SNAX CHEESE FLAVOR 23G | F49: 5.66 | L49: =G49+I49-J49-K49+H49 -> 0 | N49: =F49*L49 -> 0 | O49: =M49*F49 -> 0 | P49: =L49-M49 -> 0 | Q49: =N49-O49 -> 0 | S49: =U49+Y49+W49+AA49 -> 0 | T49: =M49-S49 -> 0
B50: 1 | C50: CHIPS & SNACK | D50: 4800092771446 | E50: FUNKY FRENCH FRY SNAX SPAGHETTI FLAVOR 23G | F50: 5.66 | L50: =G50+I50-J50-K50+H50 -> 0 | N50: =F50*L50 -> 0 | O50: =M50*F50 -> 0 | P50: =L50-M50 -> 0 | Q50: =N50-O50 -> 0 | S50: =U50+Y50+W50+AA50 -> 0 | T50: =M50-S50 -> 0
B51: 1 | C51: CHIPS & SNACK | D51: 4800016138515 | E51: GG TORTILLOS BBQ FLAVOR 100G | F51: 23.48 | L51: =G51+I51-J51-K51+H51 -> 0 | N51: =F51*L51 -> 0 | O51: =M51*F51 -> 0 | P51: =L51-M51 -> 0 | Q51: =N51-O51 -> 0 | S51: =U51+Y51+W51+AA51 -> 0 | T51: =M51-S51 -> 0
B52: 1 | C52: CHIPS & SNACK | D52: 4800016138546 | E52: GG TORTILLOS CHEESE FLAVOR 100G | F52: 23.48 | L52: =G52+I52-J52-K52+H52 -> 0 | N52: =F52*L52 -> 0 | O52: =M52*F52 -> 0 | P52: =L52-M52 -> 0 | Q52: =N52-O52 -> 0 | S52: =U52+Y52+W52+AA52 -> 0 | T52: =M52-S52 -> 0
B53: 1 | C53: CHIPS & SNACK | D53: 4800016138560 | E53: GG TORTILLOS CHEESE FLAVOR 25G | F53: 6.95 | L53: =G53+I53-J53-K53+H53 -> 0 | N53: =F53*L53 -> 0 | O53: =M53*F53 -> 0 | P53: =L53-M53 -> 0 | Q53: =N53-O53 -> 0 | S53: =U53+Y53+W53+AA53 -> 0 | T53: =M53-S53 -> 0
B54: 1 | C54: CHIPS & SNACK | D54: 4800054111228 | E54: GROWERS GARLIC FLAVOR PEANUTS 30G | F54: 12.69 | G54: 59 | K54: 2 | L54: =G54+I54-J54-K54+H54 -> 57 | M54: =46+11 -> 57 | N54: =F54*L54 -> 723.33 | O54: =M54*F54 -> 723.33 | P54: =L54-M54 -> 0 | Q54: =N54-O54 -> 0 | R54: 11-EXPIRED 6/2025 | S54: =U54+Y54+W54+AA54 -> 59 | T54: =M54-S54 -> -2 | U54: 48 | W54: 11 | X54: EXPIRED 2025 | AD54: =W54 -> 11 | AE54: =AD54*F54 -> 139.59
B55: 1 | C55: CHIPS & SNACK | D55: 4800054111280 | E55: GROWERS GARLIC FLAVOR PEANUTS 80G | F55: 34.38 | G55: 5 | K55: 2 | L55: =G55+I55-J55-K55+H55 -> 3 | M55: 3 | N55: =F55*L55 -> 103.14 | O55: =M55*F55 -> 103.14 | P55: =L55-M55 -> 0 | Q55: =N55-O55 -> 0 | S55: =U55+Y55+W55+AA55 -> 11 | T55: =M55-S55 -> -8 | U55: 11
B56: 1 | C56: CHIPS & SNACK | D56: 4800054124280 | E56: GROWERS GLAZED PILI NUTS 80G | F56: 99.04 | G56: 19 | L56: =G56+I56-J56-K56+H56 -> 19 | M56: 19 | N56: =F56*L56 -> 1881.76 | O56: =M56*F56 -> 1881.76 | P56: =L56-M56 -> 0 | Q56: =N56-O56 -> 0 | S56: =U56+Y56+W56+AA56 -> 20 | T56: =M56-S56 -> -1 | U56: 20
B57: 1 | C57: CHIPS & SNACK | D57: 4800054123221 | E57: GROWERS MIX NUTS 34G | F57: 25.88 | G57: 6 | L57: =G57+I57-J57-K57+H57 -> 6 | M57: 6 | N57: =F57*L57 -> 155.28 | O57: =M57*F57 -> 155.28 | P57: =L57-M57 -> 0 | Q57: =N57-O57 -> 0 | R57: 45836 | S57: =U57+Y57+W57+AA57 -> 6 | T57: =M57-S57 -> 0 | W57: 6 | X57: EXPIRED 2025 | AD57: =W57 -> 6 | AE57: =AD57*F57 -> 155.28
B58: 1 | C58: CHIPS & SNACK | D58: 4800054123283 | E58: GROWERS MIX NUTS 80G | F58: 61.5 | G58: 19 | K58: 3 | L58: =G58+I58-J58-K58+H58 -> 16 | M58: 16 | N58: =F58*L58 -> 984 | O58: =M58*F58 -> 984 | P58: =L58-M58 -> 0 | Q58: =N58-O58 -> 0 | S58: =U58+Y58+W58+AA58 -> 21 | T58: =M58-S58 -> -5 | U58: 18 | AA58: 3 | AB58: EXPIRED JUL 2025 | AD58: =AA58 -> 3 | AE58: =AD58*F58 -> 184.5
B59: 1 | C59: CHIPS & SNACK | D59: 4800054126284 | E59: GROWERS ONION & GARLIC ALMONDS 80G | F59: 97.04 | G59: 19 | H59: 2 | K59: 2 | L59: =G59+I59-J59-K59+H59 -> 19 | M59: =17+2 -> 19 | N59: =F59*L59 -> 1843.76 | O59: =M59*F59 -> 1843.76 | P59: =L59-M59 -> 0 | Q59: =N59-O59 -> 0 | S59: =U59+Y59+W59+AA59 -> 19 | T59: =M59-S59 -> 0 | U59: 19
B60: 1 | C60: CHIPS & SNACK | D60: 4800054113284 | E60: GROWERS ORIENTAL FLAVOR PEANUTS 80G | F60: 36.58 | G60: 22 | K60: 1 | L60: =G60+I60-J60-K60+H60 -> 21 | M60: 21 | N60: =F60*L60 -> 768.18 | O60: =M60*F60 -> 768.18 | P60: =L60-M60 -> 0 | Q60: =N60-O60 -> 0 | S60: =U60+Y60+W60+AA60 -> 22 | T60: =M60-S60 -> -1 | U60: =21+1 -> 22
B61: 1 | C61: CHIPS & SNACK | D61: 4800054121227 | E61: GROWERS SALTED CASHEW NUTS | F61: 30.77 | G61: 25 | L61: =G61+I61-J61-K61+H61 -> 25 | M61: 25 | N61: =F61*L61 -> 769.25 | O61: =M61*F61 -> 769.25 | P61: =L61-M61 -> 0 | Q61: =N61-O61 -> 0 | S61: =U61+Y61+W61+AA61 -> 25 | T61: =M61-S61 -> 0 | AA61: 25 | AB61: EXPIRED JAN 2026 | AD61: =AA61 -> 25 | AE61: =AD61*F61 -> 769.25
B62: 1 | C62: CHIPS & SNACK | D62: 4800054121289 | E62: GROWERS SALTED CASHEW NUTS 80G | F62: 90.42 | G62: 16 | K62: 3 | L62: =G62+I62-J62-K62+H62 -> 13 | M62: 13 | N62: =F62*L62 -> 1175.46 | O62: =M62*F62 -> 1175.46 | P62: =L62-M62 -> 0 | Q62: =N62-O62 -> 0 | R62: over 3 sales | S62: =U62+Y62+W62+AA62 -> 17 | T62: =M62-S62 -> -4 | U62: 17
B63: 1 | C63: CHIPS & SNACK | D63: 4800054125225 | E63: GROWERS SALTED PISTACHIO NUTS 28G | F63: 41.15 | G63: 38 | L63: =G63+I63-J63-K63+H63 -> 38 | M63: 38 | N63: =F63*L63 -> 1563.7 | O63: =M63*F63 -> 1563.7 | P63: =L63-M63 -> 0 | Q63: =N63-O63 -> 0 | S63: =U63+Y63+W63+AA63 -> 0 | T63: =M63-S63 -> 38
B64: 1 | C64: CHIPS & SNACK | D64: 4800054125287 | E64: GROWERS SALTED PISTACHIO NUTS 80G | F64: 114.79 | G64: 22 | L64: =G64+I64-J64-K64+H64 -> 22 | M64: 22 | N64: =F64*L64 -> 2525.38 | O64: =M64*F64 -> 2525.38 | P64: =L64-M64 -> 0 | Q64: =N64-O64 -> 0 | S64: =U64+Y64+W64+AA64 -> 9 | T64: =M64-S64 -> 13 | AA64: 9 | AB64: EXPIRED MAR 2026 | AD64: =AA64 -> 9 | AE64: =AD64*F64 -> 1033.11
B65: 1 | C65: CHIPS & SNACK | D65: 4800054112225 | E65: GROWERS SAVOURY HOT PEANUT 30G | F65: 12.69 | G65: 43 | L65: =G65+I65-J65-K65+H65 -> 43 | M65: 43 | N65: =F65*L65 -> 545.67 | O65: =M65*F65 -> 545.67 | P65: =L65-M65 -> 0 | Q65: =N65-O65 -> 0 | S65: =U65+Y65+W65+AA65 -> 0 | T65: =M65-S65 -> 43
B66: 1 | C66: CHIPS & SNACK | D66: 4800054112287 | E66: GROWERS SAVOURY HOT PEANUTS 80G | F66: 36.58 | G66: 22 | K66: 1 | L66: =G66+I66-J66-K66+H66 -> 21 | M66: 21 | N66: =F66*L66 -> 768.18 | O66: =M66*F66 -> 768.18 | P66: =L66-M66 -> 0 | Q66: =N66-O66 -> 0 | S66: =U66+Y66+W66+AA66 -> 22 | T66: =M66-S66 -> -1 | U66: 22
B67: 1 | C67: CHIPS & SNACK | D67: 4800054122224 | E67: GROWERS TOASTED CASHEW NUTS 28G | F67: 30.77 | G67: 9 | L67: =G67+I67-J67-K67+H67 -> 9 | M67: 9 | N67: =F67*L67 -> 276.93 | O67: =M67*F67 -> 276.93 | P67: =L67-M67 -> 0 | Q67: =N67-O67 -> 0 | S67: =U67+Y67+W67+AA67 -> 9 | T67: =M67-S67 -> 0 | AA67: 9 | AB67: EXPIRED JAN 2026 | AD67: =AA67 -> 9 | AE67: =AD67*F67 -> 276.93
B68: 1 | C68: CHIPS & SNACK | D68: 4800054122286 | E68: GROWERS TOASTED CASHEW NUTS 80G | F68: 88.75 | G68: 16 | K68: 1 | L68: =G68+I68-J68-K68+H68 -> 15 | M68: 15 | N68: =F68*L68 -> 1331.25 | O68: =M68*F68 -> 1331.25 | P68: =L68-M68 -> 0 | Q68: =N68-O68 -> 0 | R68: over 1 sales | S68: =U68+Y68+W68+AA68 -> 16 | T68: =M68-S68 -> -1 | U68: 16
B69: 1 | C69: CHIPS & SNACK | D69: 4800016680540 | E69: HONEY BUTTER POTATO CHIPS 22G | F69: 16.58 | G69: 18 | L69: =G69+I69-J69-K69+H69 -> 18 | M69: 18 | N69: =F69*L69 -> 298.44 | O69: =M69*F69 -> 298.44 | P69: =L69-M69 -> 0 | Q69: =N69-O69 -> 0 | S69: =U69+Y69+W69+AA69 -> 26 | T69: =M69-S69 -> -8 | U69: 26
B70: 1 | C70: CHIPS & SNACK | D70: 4800016680540 | E70: HONEY BUTTER POTATO CHIPS 22G | F70: 16.576 | I70: 80 | K70: 3 | L70: =G70+I70-J70-K70+H70 -> 77 | M70: 76 | N70: =F70*L70 -> 1276.352 | O70: =M70*F70 -> 1259.776 | P70: =L70-M70 -> 1 | Q70: =N70-O70 -> 16.576 | S70: =U70+Y70+W70+AA70 -> 26 | T70: =M70-S70 -> 50 | U70: 26
B71: 1 | C71: CHIPS & SNACK | D71: 4800016680267 | E71: HONEY BUTTER POTATO CHIPS 60G | F71: 39.48 | G71: 23 | K71: 8 | L71: =G71+I71-J71-K71+H71 -> 15 | M71: 15 | N71: =F71*L71 -> 592.2 | O71: =M71*F71 -> 592.2 | P71: =L71-M71 -> 0 | Q71: =N71-O71 -> 0 | S71: =U71+Y71+W71+AA71 -> 0 | T71: =M71-S71 -> 15
B72: 1 | C72: CHIPS & SNACK | D72: 4800194152839 | E72: MARTYS CHICKEN INASAL FLAVOR 26G | F72: 6.18 | G72: 87 | L72: =G72+I72-J72-K72+H72 -> 87 | M72: =50+25+12 -> 87 | N72: =F72*L72 -> 537.66 | O72: =M72*F72 -> 537.66 | P72: =L72-M72 -> 0 | Q72: =N72-O72 -> 0 | R72: 25-EXPIRED 9/19/2025 | S72: =U72+Y72+W72+AA72 -> 90 | T72: =M72-S72 -> -3 | U72: 15 | W72: =25+50 -> 75 | X72: EXPIRED 2025 50PCS HINDI EXPIRED | AD72: 25 | AE72: =AD72*F72 -> 154.5
B73: 1 | C73: CHIPS & SNACK | D73: 4800194179836 | E73: MARTYS CRACKLIN CHICKEN INASAL FLAVOR 90G | F73: 19.75 | L73: =G73+I73-J73-K73+H73 -> 0 | N73: =F73*L73 -> 0 | O73: =M73*F73 -> 0 | P73: =L73-M73 -> 0 | Q73: =N73-O73 -> 0 | S73: =U73+Y73+W73+AA73 -> 0 | T73: =M73-S73 -> 0
B74: 1 | C74: CHIPS & SNACK | D74: 4800194179904 | E74: MARTYS CRACKLIN SALT & VINEGAR 90G | F74: 19.75 | L74: =G74+I74-J74-K74+H74 -> 0 | N74: =F74*L74 -> 0 | O74: =M74*F74 -> 0 | P74: =L74-M74 -> 0 | Q74: =N74-O74 -> 0 | S74: =U74+Y74+W74+AA74 -> 0 | T74: =M74-S74 -> 0
B75: 1 | C75: CHIPS & SNACK | D75: 4800194152891 | E75: MARTYS SPICY VINEGAR 26G | F75: 6.18 | G75: 100 | L75: =G75+I75-J75-K75+H75 -> 100 | M75: 100 | N75: =F75*L75 -> 618 | O75: =M75*F75 -> 618 | P75: =L75-M75 -> 0 | Q75: =N75-O75 -> 0 | S75: =U75+Y75+W75+AA75 -> 100 | T75: =M75-S75 -> 0 | U75: 1 | W75: 99
B76: 1 | C76: CHIPS & SNACK | D76: 4800016652035 | E76: MR CHIPS NACHO CHEESE FLAVOR 26G | F76: 5.47 | H76: 24 | K76: 24 | L76: =G76+I76-J76-K76+H76 -> 0 | N76: =F76*L76 -> 0 | O76: =M76*F76 -> 0 | P76: =L76-M76 -> 0 | Q76: =N76-O76 -> 0 | S76: =U76+Y76+W76+AA76 -> 0 | T76: =M76-S76 -> 0
B77: 1 | C77: CHIPS & SNACK | D77: 4800016666445 | E77: MR. CHIPS MANAMIS MAIS 45G | F77: 7.62 | G77: 23 | H77: 15 | K77: 30 | L77: =G77+I77-J77-K77+H77 -> 8 | M77: 8 | N77: =F77*L77 -> 60.96 | O77: =M77*F77 -> 60.96 | P77: =L77-M77 -> 0 | Q77: =N77-O77 -> 0 | S77: =U77+Y77+W77+AA77 -> 36 | T77: =M77-S77 -> -28 | U77: 36
B78: 1 | C78: CHIPS & SNACK | D78: 4800016653094 | E78: MR. CHIPS NACHO CHEESE FLAVOR 100G | F78: 20.81 | L78: =G78+I78-J78-K78+H78 -> 0 | N78: =F78*L78 -> 0 | O78: =M78*F78 -> 0 | P78: =L78-M78 -> 0 | Q78: =N78-O78 -> 0 | S78: =U78+Y78+W78+AA78 -> 0 | T78: =M78-S78 -> 0
B79: 1 | C79: CHIPS & SNACK | D79: 4800361028639 | E79: NESTLE KOKO KRUNCH 20G | F79: 11.78 | G79: 1 | L79: =G79+I79-J79-K79+H79 -> 1 | N79: =F79*L79 -> 11.78 | O79: =M79*F79 -> 0 | P79: =L79-M79 -> 1 | Q79: =N79-O79 -> 11.78 | S79: =U79+Y79+W79+AA79 -> 1 | T79: =M79-S79 -> -1 | AA79: 1 | AB79: EXPIRED JUN 2025 | AD79: =AA79 -> 1 | AE79: =AD79*F79 -> 11.78
B80: 1 | C80: CHIPS & SNACK | D80: 4800016663802 | E80: NOVA COUNTRY CHEDDAR 40G | F80: 15.35 | H80: 15 | K80: 15 | L80: =G80+I80-J80-K80+H80 -> 0 | N80: =F80*L80 -> 0 | O80: =M80*F80 -> 0 | P80: =L80-M80 -> 0 | Q80: =N80-O80 -> 0 | R80: OVER 15SALES | S80: =U80+Y80+W80+AA80 -> 0 | T80: =M80-S80 -> 0
B81: 1 | C81: CHIPS & SNACK | D81: 4800016663505 | E81: NOVA COUNTRY CHEDDAR 78G | F81: 32.47 | G81: 48 | H81: 8 | K81: 17 | L81: =G81+I81-J81-K81+H81 -> 39 | M81: 39 | N81: =F81*L81 -> 1266.33 | O81: =M81*F81 -> 1266.33 | P81: =L81-M81 -> 0 | Q81: =N81-O81 -> 0 | S81: =U81+Y81+W81+AA81 -> 12 | T81: =M81-S81 -> 27 | U81: 12
B82: 1 | C82: CHIPS & SNACK | D82: 4800194104913 | E82: OHEYA CHEESE FLAVOR 28G | F82: 6.18 | G82: 87 | L82: =G82+I82-J82-K82+H82 -> 87 | M82: =18+18+1+50 -> 87 | N82: =F82*L82 -> 537.66 | O82: =M82*F82 -> 537.66 | P82: =L82-M82 -> 0 | Q82: =N82-O82 -> 0 | R82: 86-Expired 4/23/2026 & 7/2024 | S82: =U82+Y82+W82+AA82 -> 87 | T82: =M82-S82 -> 0 | U82: 1 | W82: =18+18+50 -> 86 | X82: EXPIRED 4/2026 & 2024 | AD82: =W82 -> 86 | AE82: =AD82*F82 -> 531.48
B83: 1 | C83: CHIPS & SNACK | D83: 4800194150675 | E83: OISHI CHOCO SPONGE CRUNCH 120G | F83: 37.95 | H83: 6 | K83: 6 | L83: =G83+I83-J83-K83+H83 -> 0 | N83: =F83*L83 -> 0 | O83: =M83*F83 -> 0 | P83: =L83-M83 -> 0 | Q83: =N83-O83 -> 0 | S83: =U83+Y83+W83+AA83 -> 0 | T83: =M83-S83 -> 0
B84: 1 | C84: CHIPS & SNACK | D84: 4800194116084 | E84: OISHI CRACKLINGS SALT & VINEGAR 24G | F84: 6.18 | G84: 132 | L84: =G84+I84-J84-K84+H84 -> 132 | M84: 132 | N84: =F84*L84 -> 815.76 | O84: =M84*F84 -> 815.76 | P84: =L84-M84 -> 0 | Q84: =N84-O84 -> 0 | R84: 56-EXPIRED 11/26/2024 | S84: =U84+Y84+W84+AA84 -> 135 | T84: =M84-S84 -> -3 | U84: 29 | W84: =56+50 -> 106 | X84: EXPIRED 2024 50PCS HINDI EXPIRED | AD84: 56 | AE84: =AD84*F84 -> 346.08
B85: 1 | C85: CHIPS & SNACK | D85: 897399001028 | E85: OISHI CRACKLINGS SALT & VINEGAR 90G | F85: 21.97 | G85: 17 | L85: =G85+I85-J85-K85+H85 -> 17 | M85: =15+2 -> 17 | N85: =F85*L85 -> 373.49 | O85: =M85*F85 -> 373.49 | P85: =L85-M85 -> 0 | Q85: =N85-O85 -> 0 | S85: =U85+Y85+W85+AA85 -> 21 | T85: =M85-S85 -> -4 | U85: 6 | W85: 15
B86: 1 | C86: CHIPS & SNACK | D86: 4800194104869 | E86: OISHI CRISPY PATATA 24G | F86: 6.18 | G86: 49 | H86: 30 | K86: 30 | L86: =G86+I86-J86-K86+H86 -> 49 | M86: 49 | N86: =F86*L86 -> 302.82 | O86: =M86*F86 -> 302.82 | P86: =L86-M86 -> 0 | Q86: =N86-O86 -> 0 | S86: =U86+Y86+W86+AA86 -> 53 | T86: =M86-S86 -> -4 | U86: 4 | W86: 49 | X86: EXPIRED MAY 2026 | AD86: =W86 -> 49 | AE86: =AD86*F86 -> 302.82
B87: 1 | C87: CHIPS & SNACK | D87: 4800194177863 | E87: OISHI CRISPY PATATA 85G | F87: 21.97 | G87: 32 | L87: =G87+I87-J87-K87+H87 -> 32 | M87: =15+17 -> 32 | N87: =F87*L87 -> 703.04 | O87: =M87*F87 -> 703.04 | P87: =L87-M87 -> 0 | Q87: =N87-O87 -> 0 | R87: 32-Expired 6/2026 | S87: =U87+Y87+W87+AA87 -> 36 | T87: =M87-S87 -> -4 | U87: 4 | W87: =17+15 -> 32 | X87: EXPIRED 2024 2025 15PCS JUNE 2026 | AD87: 15 | AE87: =AD87*F87 -> 329.55
B88: 1 | C88: CHIPS & SNACK | D88: 4800194116619 | E88: OISHI FISH CRACKERS 24G | F88: 6.43 | L88: =G88+I88-J88-K88+H88 -> 0 | N88: =F88*L88 -> 0 | O88: =M88*F88 -> 0 | P88: =L88-M88 -> 0 | Q88: =N88-O88 -> 0 | S88: =U88+Y88+W88+AA88 -> 0 | T88: =M88-S88 -> 0
B89: 1 | C89: CHIPS & SNACK | D89: 4800194136648 | E89: OISHI FISHDA FISH KROPECK 22G | F89: 6.18 | G89: 90 | L89: =G89+I89-J89-K89+H89 -> 90 | M89: =7+49+34 -> 90 | N89: =F89*L89 -> 556.2 | O89: =M89*F89 -> 556.2 | P89: =L89-M89 -> 0 | Q89: =N89-O89 -> 0 | R89: 56-Expired 5/2026 & 11/2024 | S89: =U89+Y89+W89+AA89 -> 94 | T89: =M89-S89 -> -4 | U89: 38 | W89: =7+49 -> 56 | X89: EXPIRED 2024 49PCS MAY 2026 | AD89: 49 | AE89: =AD89*F89 -> 302.82
B90: 1 | C90: CHIPS & SNACK | D90: 4800194179898 | E90: OISHI MARTYS CRACKLIN SPICY VINEGAR 90G | F90: 19.75 | L90: =G90+I90-J90-K90+H90 -> 0 | N90: =F90*L90 -> 0 | O90: =M90*F90 -> 0 | P90: =L90-M90 -> 0 | Q90: =N90-O90 -> 0 | S90: =U90+Y90+W90+AA90 -> 0 | T90: =M90-S90 -> 0
B91: 1 | C91: CHIPS & SNACK | D91: 4800194115247 | E91: OISHI MOBSTERS POPCORN CARAMEL & CHEESE | F91: 15.75 | G91: 54 | L91: =G91+I91-J91-K91+H91 -> 54 | M91: 54 | N91: =F91*L91 -> 850.5 | O91: =M91*F91 -> 850.5 | P91: =L91-M91 -> 0 | Q91: =N91-O91 -> 0 | R91: 45620 | S91: =U91+Y91+W91+AA91 -> 54 | T91: =M91-S91 -> 0 | W91: 54 | X91: EXPIRED 2024 | AD91: =W91 -> 54 | AE91: =AD91*F91 -> 850.5
B92: 1 | C92: CHIPS & SNACK | D92: 4800194104982 | E92: OISHI ONION RINGS 16G | F92: 6.43 | G92: 50 | L92: =G92+I92-J92-K92+H92 -> 50 | M92: 50 | N92: =F92*L92 -> 321.5 | O92: =M92*F92 -> 321.5 | P92: =L92-M92 -> 0 | Q92: =N92-O92 -> 0 | S92: =U92+Y92+W92+AA92 -> 50 | T92: =M92-S92 -> 0 | W92: 50 | X92: EXPIRED 2024 | AD92: =W92 -> 50 | AE92: =AD92*F92 -> 321.5
B93: 1 | C93: CHIPS & SNACK | D93: 4800194116466 | E93: OISHI PILLOWS CHOCO FLAVOR 38G | F93: 8.61 | G93: 101 | L93: =G93+I93-J93-K93+H93 -> 101 | M93: =51+50 -> 101 | N93: =F93*L93 -> 869.61 | O93: =M93*F93 -> 869.61 | P93: =L93-M93 -> 0 | Q93: =N93-O93 -> 0 | R93: 45489 | S93: =U93+Y93+W93+AA93 -> 101 | T93: =M93-S93 -> 0 | W93: =51+50 -> 101 | X93: EXPIRED 2024 | AD93: =W93 -> 101 | AE93: =AD93*F93 -> 869.61
B94: 1 | C94: CHIPS & SNACK | D94: 4800194114462 | E94: OISHI PILLOWS CHOCOLATE 150G | F94: 37.95 | H94: 6 | K94: 6 | L94: =G94+I94-J94-K94+H94 -> 0 | N94: =F94*L94 -> 0 | O94: =M94*F94 -> 0 | P94: =L94-M94 -> 0 | Q94: =N94-O94 -> 0 | S94: =U94+Y94+W94+AA94 -> 0 | T94: =M94-S94 -> 0
B95: 1 | C95: CHIPS & SNACK | D95: 4800194152327 | E95: OISHI PILLOWS UBE-FILLED CRACKERS 38G | F95: 8.61 | L95: =G95+I95-J95-K95+H95 -> 0 | N95: =F95*L95 -> 0 | O95: =M95*F95 -> 0 | P95: =L95-M95 -> 0 | Q95: =N95-O95 -> 0 | S95: =U95+Y95+W95+AA95 -> 0 | T95: =M95-S95 -> 0
B96: 1 | C96: CHIPS & SNACK | D96: 4800194152709 | E96: OISHI PODS PEA SNACK 28G | F96: 6.43 | L96: =G96+I96-J96-K96+H96 -> 0 | N96: =F96*L96 -> 0 | O96: =M96*F96 -> 0 | P96: =L96-M96 -> 0 | Q96: =N96-O96 -> 0 | S96: =U96+Y96+W96+AA96 -> 0 | T96: =M96-S96 -> 0
B97: 1 | C97: CHIPS & SNACK | D97: 4800194115063 | E97: OISHI POTATO CHIPS PLAIN SALTED 60G | F97: 30.75 | L97: =G97+I97-J97-K97+H97 -> 0 | N97: =F97*L97 -> 0 | O97: =M97*F97 -> 0 | P97: =L97-M97 -> 0 | Q97: =N97-O97 -> 0 | S97: =U97+Y97+W97+AA97 -> 0 | T97: =M97-S97 -> 0
B98: 1 | C98: CHIPS & SNACK | D98: 4800194104777 | E98: OISHI POTATO FRIES CHEESE FLAVOR 21G | F98: 6.43 | G98: 5 | L98: =G98+I98-J98-K98+H98 -> 5 | M98: 5 | N98: =F98*L98 -> 32.15 | O98: =M98*F98 -> 32.15 | P98: =L98-M98 -> 0 | Q98: =N98-O98 -> 0 | R98: 45613 | S98: =U98+Y98+W98+AA98 -> 5 | T98: =M98-S98 -> 0 | W98: 5 | X98: EXPIRED 2024 | AD98: =W98 -> 5 | AE98: =AD98*F98 -> 32.15
B99: 1 | C99: CHIPS & SNACK | D99: 4800194177771 | E99: OISHI POTATO FRIES CHEESE FLAVOR 90G | F99: 22.86 | L99: =G99+I99-J99-K99+H99 -> 0 | N99: =F99*L99 -> 0 | O99: =M99*F99 -> 0 | P99: =L99-M99 -> 0 | Q99: =N99-O99 -> 0 | S99: =U99+Y99+W99+AA99 -> 0 | T99: =M99-S99 -> 0
B100: 1 | C100: CHIPS & SNACK | D100: 4800194131230 | E100: OISHI POTATO FRIES PLAIN 90G | F100: 22.86 | L100: =G100+I100-J100-K100+H100 -> 0 | N100: =F100*L100 -> 0 | O100: =M100*F100 -> 0 | P100: =L100-M100 -> 0 | Q100: =N100-O100 -> 0 | S100: =U100+Y100+W100+AA100 -> 0 | T100: =M100-S100 -> 0
...

Sheet VB-final
A1: VARIANCE BREAKDOWN (CONVIE)
A2: =PRINTING!B2 -> AS OF JUNE 2026
A3: OVER
A4: BARCODE | B4: PRODUCT NAME | C4: UNIT COST | D4: TOTAL | E4: ACTUAL | F4: VARIANCE - QUANTITY | G4: VARIANCE - COST | H4: REMARKS / CAUSE OF VARIANCE
A5: 4800888139283 | B5: CREAMSILK GREEN 11ML | C5: 6.17 | D5: 1 | E5: 2 | F5: -1 | G5: -6.17
A6: 4800888217523 | B6: DOVE SERUM CONDITIONER AMINO RESTORE 10ML | C6: 6.48 | D6: 306 | E6: 311 | F6: -5 | G6: -32.4
A7: 4801234146078 | B7: GLADE SG FRESH LEMON 180G VALUE PACK | C7: 267 | D7: 5 | E7: 6 | F7: -1 | G7: -267
A8: 4902430522809 | B8: HEAD & SHOULDER ANTI-DANDRUFF SHAMPOO ULTRA MEN COOL MENTHOL 12ML | C8: 6.82 | D8: 4 | E8: 5 | F8: -1 | G8: -6.82
A9: 4801010342717 | B9: MODESS REGULAR W/ WINGS 9+1 PADS | C9: 37.25 | D9: 13 | E9: 14 | F9: -1 | G9: -37.25
A10: 4808888004181 | B10: PALMOLIVE VIOLET BUY 11 GET 1 FREE | C10: 57.77 | D10: 114 | E10: 115 | F10: -1 | G10: -57.77
A11: 4902430634014 | B11: PANTENE HAIR FALL CONTROL SUPPLEMENT CONDITIONER 13ML | C11: 7.33 | D11: 140 | E11: 141 | F11: -1 | G11: -7.33
A12: 4800888151100 | B12: REXONA WOMEN DEO LOTION PASSION 3ML | C12: 6.6 | D12: 9 | E12: 10 | F12: -1 | G12: -6.6
A13: 4902430935616 | B13: SAFEGUARD FLORAL PINK W/ ALOE 130G | C13: 47.2 | D13: 38 | E13: 39 | F13: -1 | G13: -47.2
A14: 4902430381772 | B14: SAFEGUARD IVORY WHITE CARE 60G | C14: 18.64 | D14: 133 | E14: 136 | F14: -3 | G14: -55.92
A15: 4902430934800 | B15: SAFEGUARD PURE WHITE 130G | C15: 47.2 | D15: 40 | E15: 47 | F15: -7 | G15: -330.4
A16: 4902430222891 | B16: SAFEGUARD PURE WHITE SUPER SAVINGS PACK 175G | C16: 55.86 | D16: 21 | E16: 31 | F16: -10 | G16: -558.6
... A52: 200049 | B52: HBW MATRIX BALLPEN RED | C52: 5 | D52: 19 | E52: 20 | F52: -1 | G52: -5
D53: =SUM(D5:D52) -> 3127 | E53: =SUM(E5:E52) -> 3777 | F53: =SUM(F5:F52) -> -650 | G53: =SUM(G5:G52) -> -11977.6
A54: RETURN
A55: BARCODE | B55: PRODUCT NAME | C55: UNIT COST | F55: VARIANCE - QUANTITY | G55: VARIANCE - COST | H55: REMARKS / CAUSE OF VARIANCE
F57: =SUM(F56:F56) -> 0 | G57: =SUM(G56:G56) -> 0
A59: SHORT
A60: BARCODE | B60: PRODUCT NAME | C60: UNIT COST | D60: TOTAL | E60: ACTUAL | F60: VARIANCE - QUANTITY | G60: VARIANCE - COST | H60: REMARKS / CAUSE OF VARIANCE
A61: 4809011681095 | B61: BOY BAWANG CORNICK ADOBO 100G | C61: 16.03 | D61: 13 | E61: 12 | F61: 1 | G61: 16.03
A62: 4809011681507 | B62: BOY BAWANG CORNICK BBQ FLAVOR 100G | C62: 16.03 | D62: 66 | E62: 65 | F62: 1 | G62: 16.03
A63: 4800016110535 | B63: CHICHARRON NI MANG JUAN PAOMBONG 26G | C63: 6.83 | D63: 29 | E63: 28 | F63: 1 | G63: 6.83
A64: 4800016110542 | B64: CHICHARRON NI MANG JUAN SUKAT SILI 26G | C64: 6.83 | D64: 30 | E64: 29 | F64: 1 | G64: 6.83
A65: 4800216120013 | B65: CLOVER CHEESE 24G | C65: 7.51 | D65: 86 | E65: 84 | F65: 2 | G65: 15.02
A66: 4800216110069 | B66: CLOVER CHIPS CHEESE 55G | C66: 22.19 | D66: 3 | F66: 3 | G66: 66.57
A67: 4800194116114 | B67: CORN OLE BARBECUE FLAVOR 22G | C67: 6.18 | D67: 77 | E67: 73 | F67: 4 | G67: 24.72
A68: 4800016680540 | B68: HONEY BUTTER POTATO CHIPS 22G | C68: 16.58 | D68: 95 | E68: 94 | F68: 1 | G68: 16.58
A69: 4800361028639 | B69: NESTLE KOKO KRUNCH 20G | C69: 11.78 | D69: 1 | F69: 1 | G69: 11.78
A70: 4800194177962 | B70: OISHI PRAWN CRACKERS SPICY FLAVOR 90G | C70: 21.97 | D70: 17 | E70: 16 | F70: 1 | G70: 21.97
A71: 4800116099020 | B71: BUTTER CREAM ENSAYMADA CRACKERS 10X25G | C71: 58.45 | D71: 9 | E71: 8 | F71: 1 | G71: 58.45
A72: 4800552888059 | B72: CHIPS DELIGHT CHOCOLATE CHIP COOKIES 80G | C72: 30.04 | D72: 9 | E72: 8 | F72: 1 | G72: 30.04
A73: 4800016627262 | B73: CHOCO KNOTS CHOCOLATE 28G | C73: 7.48 | D73: 24 | E73: 22 | F73: 2 | G73: 14.96
A74: 4806502726822 | B74: GAR NEUBAKE WHITE BREAD 450G | C74: 53.9 | D74: 2 | E74: 1 | F74: 1 | G74: 53.9
A75: 8998389124184 | B75: KUKIS KELAPA COCONUT 60G | C75: 12.77 | D75: 1 | F75: 1 | G75: 12.77
A76: 4800016083778 | B76: MAGIC CHIPS SOUR CREAM AND ONION 28G | C76: 6.8 | D76: 3 | F76: 3 | G76: 20.4
A77: 4807770100703 | B77: NISSIN BREAD STIX 20G | C77: 5.68 | D77: 1 | F77: 1 | G77: 5.68
A78: 8886001038011 | B78: BENGBENG 26.5G | C78: 7.5 | D78: 165 | E78: 161 | F78: 4 | G78: 30
A79: 4800818809361 | B79: FRUTOS MINIBITS SOUR 10G | C79: 1.77 | D79: 2 | F79: 2 | G79: 3.54
A80: 4806533325254 | B80: GOYA TAKE IT 2F 2+1 | C80: 33.76 | D80: 11 | E80: 9 | F80: 2 | G80: 67.52
A81: 4800214061271 | B81: MENTOS MINT CANDY 50 PCS 135G | C81: 38 | D81: 5 | E81: 4 | F81: 1 | G81: 38
A82: 69025310 | B82: SNICKERS 20G | C82: 13.77 | D82: 18 | E82: 12 | F82: 6 | G82: 82.62
A83: 4800016022258 | B83: GREAT TASTE CHOCO TWIN PACK 50G | C83: 11.76 | D83: 99 | E83: 98 | F83: 1 | G83: 11.76
A84: 4800016022180 | B84: GREAT TASTE WHITE CREMA TWINPACK 50G | C84: 11.39 | D84: 2 | F84: 2 | G84: 22.78
A85: 4800016021169 | B85: GREAT TASTE ORIGINAL TWIN PACK 33G | C85: 9.26 | D85: 122 | E85: 117 | F85: 5 | G85: 46.3
A86: 4800361423588 | B86: NESCAFE CREAMY WHITE SUGAR FREE TWIN PACK 11.2 GRAMS | C86: 13.21 | D86: 32 | E86: 23 | F86: 9 | G86: 118.89
A87: 4800361423052 | B87: NESTLE LEMONADE CUCUMBER 200G | C87: 202 | D87: 1 | F87: 1 | G87: 202
A88: 4807770272813 | B88: LM LA PAZ BATCHOY 55G | C88: 15 | D88: 10 | E88: 9 | F88: 1 | G88: 15
A89: 4800575140370 | B89: ALASKA EVAPORADA CREAMER 360ML | C89: 35.15 | D89: 18 | E89: 17 | F89: 1 | G89: 35.15
A90: 748485800448 | B90: ARGENTINA MEAT LOAF 250G | C90: 32.8 | D90: 2 | E90: 1 | F90: 1 | G90: 32.8
A91: 748485801728 | B91: LUCKY 7 CARNE NORTE 150G | C91: 22.45 | D91: 17 | E91: 16 | F91: 1 | G91: 22.45
A92: 748485802220 | B92: WOW ULAM MECHADO 155G | C92: 22.59 | D92: 1 | F92: 1 | G92: 22.59
A93: 888123456782035 | B93: BAIS SUGAR WASH 1/4 | C93: 13.85 | D93: 47 | E93: 42 | F93: 5 | G93: 69.25
A94: 4800888607959 | B94: KNORR SHRIMP BROTH CUBE 10G | C94: 6.02 | D94: 91 | E94: 65 | F94: 26 | G94: 156.52
A95: 4804888804189 | B95: MAMA SITAS ACHUETE POWDER 10G | C95: 20.8 | D95: 19 | E95: 18 | F95: 1 | G95: 20.8
A96: 014285000068 | B96: UFC BANANA CATSUP 320G | C96: 26 | D96: 1 | F96: 1 | G96: 26
A97: 4800034017243 | B97: HAPEE EXPLOSIVE MENTHOL RED 55G | C97: 10.95 | D97: 71 | E97: 52 | F97: 19 | G97: 208.05
A98: 4800888160027 | B98: REXONA MEN DEO LOTION ICE COOL 3ML | C98: 6.73 | D98: 31 | E98: 30 | F98: 1 | G98: 6.73
A99: 4806519890981 | B99: UNI KERATIN DETOX & NOURISH GOLD 20G | C99: 6 | D99: 125 | E99: 124 | F99: 1 | G99: 6
A100: 4806501708102 | B100: CHAMPION FABRICON PINK FRESH 28ML | C100: 5.02 | D100: 84 | E100: 82 | F100: 2 | G100: 10.04
A101: 4902430873703 | B101: DOWNY EXPERT KONTRA KULOB 23ML | C101: 6.12 | D101: 345 | E101: 343 | F101: 2 | G101: 12.24
A102: 4902430389549 | B102: JOY SAFEGUARD ANTIBAC 17ML | C102: 5.78 | D102: 95 | E102: 94 | F102: 1 | G102: 5.78
A103: 8934868139362 | B103: SURF FABCON CHARCOAL FRESH 25ML | C103: 5.41 | D103: 109 | E103: 108 | F103: 1 | G103: 5.41
A104: 8934868094982 | B104: SURF FABCON FRENCH PERFUME 25ML | C104: 5.41 | D104: 207 | E104: 204 | F104: 3 | G104: 16.23
A105: 4800888151834 | B105: SURF FABCON TAWAS 61G | C105: 6.37 | D105: 64 | E105: 54 | F105: 10 | G105: 63.7
A106: 8998866605076 | B106: WINGS TOTAL CARE W/ LAUNDRY SANITIZER 60G | C106: 5 | D106: 9 | E106: 8 | F106: 1 | G106: 5
A107: 4800361388313 | B107: NESTLE CHUCKIE 180ML | C107: 19.47 | D107: 17 | E107: 16 | F107: 1 | G107: 19.47
A108: 4800361395687 | B108: NESTLE CHUCKIE BULILIT PACK 110ML | C108: 11.5 | D108: 29 | E108: 28 | F108: 1 | G108: 11.5
A109: 4800116136008 | B109: OTC BUTTER CREAM CHEESE SPREAD 17G | C109: 4.48 | D109: 1 | F109: 1 | G109: 4.48
A110: 8935001721550 | B110: OTC CHUPA CHUPS MILKY CARAMEL LOLLIPOP 9G | C110: 3.6 | D110: 1 | F110: 1 | G110: 3.6
A111: 8935001721567 | B111: OTC CHUPA CHUPS STRAWBERRY & CREAM FLAVOR 9G | C111: 3.6 | D111: 2 | F111: 2 | G111: 7.2
A112: 888123456781549 | B112: OTC DYNAMITE CHOCO MINT RETAIL | C112: 0.76 | D112: 53 | E112: 50 | F112: 3 | G112: 2.28
A113: 888123456781258 | B113: OTC MAXX CHERRY | C113: 0.76 | D113: 57 | F113: 57 | G113: 43.32
A114: 75051030176 | B114: OTC SKYFLAKES ONION & CHIVES | C114: 6.025 | D114: 11 | E114: 3 | F114: 8 | G114: 48.2
A115: 4800116099006 | B115: OTC BUTTER CREAM ENSAYMADA 25G | C115: 6.15 | D115: 1 | F115: 1 | G115: 6.15
A116: 888123456782039 | B116: OTC SUPERLAMIG PEPPERMINT | C116: 0.76 | D116: 22 | E116: 8 | F116: 14 | G116: 10.64
A117: 750515031043 | B117: OTC SKYFLAKES CONDENSADA | C117: 6.025 | D117: 7 | E117: 6 | F117: 1 | G117: 6.025
A118: 4807770101076 | B118: NISSIN CUBEE WAFER 25G | C118: 10 | D118: 2 | F118: 2 | G118: 20
A119: 7359 | B119: SAFEGUARD CLASSIC BEIGE | C119: 20.56 | D119: 17 | E119: 16 | F119: 1 | G119: 20.56
A120: 80088240040 | B120: CREAMSILK KERATIN & REBOND | C120: 0 | D120: 5 | E120: 3 | F120: 2 | G120: 0
D121: =SUM(D76:D120) -> 2032 | E121: =SUM(E61:E120) -> 2261 | F121: =SUM(F61:F120) -> 233 | G121: =SUM(G61:G120) -> 1965.135

Sheet JUNE SALES-
A1: SALES
A2: =PRINTING!B2 -> AS OF JUNE 2026
A3: DATE | B3: PARTICULAR | C3: TRANSACTION NO: | D3: DESCRIPTION | E3: QTY. | F3: COST PRICE | G3: UNIT PRICE | H3: CASH SALE | I3: ACCOUNT RECEIVABLE | J3: SALES DISCOUNT | K3: NET SALES | L3: COGS
A4: 06/01/2026 | B4: 4800631001928 | C4: 0-144075 | D4: BOY BAWANG ASSORTED NUTS 85G | E4: 2 | F4: 19.1 | G4: 22 | H4: =E4*G4 -> 44 | J4: 0 | K4: =H4+I4-J4 -> 44 | L4: =E4*F4 -> 38.2
A5: 06/01/2026 | B5: 8998866605076 | C5: 0-144076 | D5: WINGS TOTAL CARE W/ LAUNDRY SANITIZER 60G | E5: 2 | F5: 5 | G5: 5.75 | H5: =E5*G5 -> 11.5 | J5: 0 | K5: =H5+I5-J5 -> 11.5 | L5: =E5*F5 -> 10
A6: 06/01/2026 | B6: 4800047841040 | C6: 0-144076 | D6: DEL FABCON BLOSSOM RUSH 22ML | E6: 6 | F6: 3.72 | G6: 4.5 | H6: =E6*G6 -> 27 | J6: 0 | K6: =H6+I6-J6 -> 27 | L6: =E6*F6 -> 22.32
A7: 06/01/2026 | B7: 4800010075922 | C7: 0-144076 | D7: PRESTO CREAMS PEANUT BUTTER 300G | E7: 1 | F7: 59.51 | G7: 68.5 | H7: =E7*G7 -> 68.5 | J7: 0 | K7: =H7+I7-J7 -> 68.5 | L7: =E7*F7 -> 59.51
A8: 06/01/2026 | B8: 4800888221049 | C8: 0-144076 | D8: SURF POWDER ROSE FRESH 6+1 | E8: 1 | F8: 38.25 | G8: 44 | H8: =E8*G8 -> 44 | J8: 0 | K8: =H8+I8-J8 -> 44 | L8: =E8*F8 -> 38.25
A9: 06/01/2026 | B9: 4800116135001 | C9: 0-144078 | D9: OTC BUTTER CREAM CHOCOLATE SPREAD 17G | E9: 1 | F9: 4.12 | G9: 5.25 | H9: =E9*G9 -> 5.25 | J9: 0 | K9: =H9+I9-J9 -> 5.25 | L9: =E9*F9 -> 4.12
A10: 06/01/2026 | B10: 4807770122705 | C10: 0-144078 | D10: OTC MONDE CHOCO PUFF | E10: 1 | F10: 8.15 | G10: 9.5 | H10: =E10*G10 -> 9.5 | J10: 0 | K10: =H10+I10-J10 -> 9.5 | L10: =E10*F10 -> 8.15
A11: 06/01/2026 | B11: 8998389124184 | C11: 0-144079 | D11: KUKIS KELAPA COCONUT 60G | E11: 1 | F11: 12.77 | G11: 14.75 | H11: =E11*G11 -> 14.75 | J11: 0 | K11: =H11+I11-J11 -> 14.75 | L11: =E11*F11 -> 12.77
A12: 06/01/2026 | B12: 888123456781304 | C12: 0-144079 | D12: PANI-PEANUT | E12: 1 | F12: 90 | G12: 120 | H12: =E12*G12 -> 120 | J12: 0 | K12: =H12+I12-J12 -> 120 | L12: =E12*F12 -> 90
A13: 06/01/2026 | B13: 4800216121058 | C13: 0-144080 | D13: CHEEZY CORN CRUNCH CHEESE 70G | E13: 1 | F13: 27.5 | G13: 30 | H13: =E13*G13 -> 30 | J13: 0 | K13: =H13+I13-J13 -> 30 | L13: =E13*F13 -> 27.5
A14: 06/01/2026 | B14: 4800888151100 | C14: 0-144080 | D14: REXONA WOMEN DEO LOTION PASSION 3ML | E14: 2 | F14: 6.6 | G14: 7.75 | H14: =E14*G14 -> 15.5 | J14: 0 | K14: =H14+I14-J14 -> 15.5 | L14: =E14*F14 -> 13.2
A15: 06/01/2026 | B15: 4800888147240 | C15: 0-144080 | D15: CLOSE UP MENTHOL FRESH 2X11G | E15: 1 | F15: 7.75 | G15: 9 | H15: =E15*G15 -> 9 | J15: 0 | K15: =H15+I15-J15 -> 9 | L15: =E15*F15 -> 7.75
... A37: 06/02/2026 | B37: 4800888602725 | C37: 0-144102 | D37: KNORR PORK BROTH CUBE 10G | E37: 2 | F37: 6.02 | G37: 7.25 | H37: =E37*G37 -> 14.5 | J37: 0 | K37: =H37+I37-J37 -> 14.5 | L37: =E37*F37 -> 12.04
A38: 06/02/2026 | B38: 4800361393645 | C38: 0-144103 | D38: NESCAFE CLASSIC RESEALABLE 50G | E38: 1 | G38: 58 | H38: =E38*G38 -> 58 | J38: 0 | K38: =H38+I38-J38 -> 58 | L38: =E38*F38 -> 0
A39: 06/02/2026 | B39: 4800631001928 | C39: 0-144104 | D39: BOY BAWANG ASSORTED NUTS 85G | E39: 2 | F39: 19.1 | G39: 22 | H39: =E39*G39 -> 44 | J39: 0 | K39: =H39+I39-J39 -> 44 | L39: =E39*F39 -> 38.2
A40: 06/02/2026 | B40: 4800361415347 | C40: 0-144105 | D40: NESCAFE ORIGINAL TWIN PACK 56G | E40: 1 | F40: 13.32 | G40: 15.5 | H40: =E40*G40 -> 15.5 | J40: 0 | K40: =H40+I40-J40 -> 15.5 | L40: =E40*F40 -> 13.32
A41: 06/02/2026 | B41: 888123456781858 | C41: 0-144106 | D41: OTC DYNAMITE MELON MINT RETAIL | E41: 5 | F41: 0.76 | G41: 1 | H41: =E41*G41 -> 5 | J41: 0 | K41: =H41+I41-J41 -> 5 | L41: =E41*F41 -> 3.8
A42: 06/02/2026 | B42: 8998666001702 | C42: 0-144107 | D42: KOPIKO BLACK 3IN1 TWINPACK 60G | E42: 1 | F42: 12.56 | G42: 14.25 | H42: =E42*G42 -> 14.25 | J42: 0 | K42: =H42+I42-J42 -> 14.25 | L42: =E42*F42 -> 12.56
A43: 06/02/2026 | B43: 4808680221250 | C43: 0-144110 | D43: KNORR CREAM OF MUSHROOM SOUP MIX 70G | E43: 1 | F43: 51.97 | G43: 60 | H43: =E43*G43 -> 60 | J43: 0 | K43: =H43+I43-J43 -> 60 | L43: =E43*F43 -> 51.97
A44: 06/02/2026 | B44: 4800888218940 | C44: 0-144110 | D44: SURF POWDER ANTIBACTERIAL 60G | E44: 2 | F44: 6.37 | G44: 7.5 | H44: =E44*G44 -> 15 | J44: 0 | K44: =H44+I44-J44 -> 15 | L44: =E44*F44 -> 12.74
A45: 06/02/2026 | B45: 4801958250006 | C45: 0-144110 | D45: AJI-NO-MOTO UMAMI SEASONING 250G | E45: 3 | F45: 60.4 | G45: 70 | H45: =E45*G45 -> 210 | J45: 0 | K45: =H45+I45-J45 -> 210 | L45: =E45*F45 -> 181.2
A46: 06/02/2026 | B46: 4800024570611 | C46: 0-144110 | D46: DM PINEAPPLE TIDBITS 115G | E46: 3 | F46: 15.91 | G46: 18.5 | H46: =E46*G46 -> 55.5 | J46: 0 | K46: =H46+I46-J46 -> 55.5 | L46: =E46*F46 -> 47.73
A47: 06/02/2026 | B47: 4801668500224 | C47: 0-144110 | D47: DATU PUTI SOY SAUCE 1L | E47: 3 | F47: 51 | G47: 60.25 | H47: =E47*G47 -> 180.75 | J47: 0 | K47: =H47+I47-J47 -> 180.75 | L47: =E47*F47 -> 153
A48: 06/02/2026 | B48: 4808647020094 | C48: 0-144110 | D48: EDEN CHEESE ORIGINAL 160G | E48: 1 | F48: 53.81 | G48: 62 | H48: =E48*G48 -> 62 | J48: 0 | K48: =H48+I48-J48 -> 62 | L48: =E48*F48 -> 53.81
A49: 06/02/2026 | B49: 4800361061322 | C49: 0-144110 | D49: NESTLE ALL PURPOSE CREAM 250ML | E49: 1 | F49: 67.29 | G49: 77.5 | H49: =E49*G49 -> 77.5 | J49: 0 | K49: =H49+I49-J49 -> 77.5 | L49: =E49*F49 -> 67.29
A50: 06/02/2026 | B50: 4800361419307 | C50: 0-144110 | D50: NESTLE CARNATION CONDENSADA 300ML | E50: 1 | F50: 64.49 | G50: 74.25 | H50: =E50*G50 -> 74.25 | J50: 0 | K50: =H50+I50-J50 -> 74.25 | L50: =E50*F50 -> 64.49
... A102: 06/03/2026 | B102: 4800575140370 | C102: 0-144148 | D102: ALASKA EVAPORADA CREAMER 360ML | E102: 1 | F102: 35.15 | G102: 41 | H102: =E102*G102 -> 41 | J102: 0 | K102: =H102+I102-J102 -> 41 | L102: =E102*F102 -> 35.15
A103: 06/03/2026 | B103: 748485800011 | C103: 0-144148 | D103: ARGENTINA CORN BEEF 175G | E103: 1 | G103: 47.5 | H103: =E103*G103 -> 47.5 | J103: 0 | K103: =H103+I103-J103 -> 47.5 | L103: =E103*F103 -> 0
A104: 06/03/2026 | B104: 4800888602718 | C104: 0-144148 | D104: KNORR CHICKEN BROTH CUBE 10G | E104: 1 | F104: 6.02 | G104: 7.25 | H104: =E104*G104 -> 7.25 | J104: 0 | K104: =H104+I104-J104 -> 7.25 | L104: =E104*F104 -> 6.02
A105: 06/03/2026 | B105: 4800054111228 | C105: 0-144149 | D105: GROWERS GARLIC FLAVOR PEANUTS 30G | E105: 1 | F105: 12.69 | G105: 14.75 | H105: =E105*G105 -> 14.75 | J105: 0 | K105: =H105+I105-J105 -> 14.75 | L105: =E105*F105 -> 12.69
A106: 06/03/2026 | B106: 888123456781258 | C106: 0-144150 | D106: OTC MAXX CHERRY | E106: 6 | F106: 0.76 | G106: 1 | H106: =E106*G106 -> 6 | J106: 0 | K106: =H106+I106-J106 -> 6 | L106: =E106*F106 -> 4.56
A107: 06/03/2026 | B107: 888123456781549 | C107: 0-144152 | D107: OTC DYNAMITE CHOCO MINT RETAIL | E107: 1 | F107: 0.76 | G107: 1 | H107: =E107*G107 -> 1 | J107: 0 | K107: =H107+I107-J107 -> 1 | L107: =E107*F107 -> 0.76
A108: 06/03/2026 | B108: 888123456781858 | C108: 0-144152 | D108: OTC DYNAMITE MELON MINT RETAIL | E108: 4 | F108: 0.76 | G108: 1 | H108: =E108*G108 -> 4 | J108: 0 | K108: =H108+I108-J108 -> 4 | L108: =E108*F108 -> 3.04
A109: 06/03/2026 | B109: 4806500472639 | C109: 0-144155 | D109: FAVORITO PANCIT CANTON 400G | E109: 2 | F109: 48.6 | G109: 56 | H109: =E109*G109 -> 112 | J109: 0 | K109: =H109+I109-J109 -> 112 | L109: =E109*F109 -> 97.2
A110: 06/03/2026 | B110: 4800361410816 | C110: 0-144157 | D110: NESTLE BEARBRAND SWAK PACK 33G | E110: 2 | F110: 10.64 | G110: 12.25 | H110: =E110*G110 -> 24.5 | J110: 0 | K110: =H110+I110-J110 -> 24.5 | L110: =E110*F110 -> 21.28
A111: 06/03/2026 | B111: 888123456781858 | C111: 0-144158 | D111: OTC DYNAMITE MELON MINT RETAIL | E111: 2 | F111: 0.76 | G111: 1 | H111: =E111*G111 -> 2 | J111: 0 | K111: =H111+I111-J111 -> 2 | L111: =E111*F111 -> 1.52
A112: 06/03/2026 | B112: 748485401492 | C112: 0-144160 | D112: BIRCH TREE 33G | E112: 1 | F112: 7.85 | G112: 12 | H112: =E112*G112 -> 12 | J112: 0 | K112: =H112+I112-J112 -> 12 | L112: =E112*F112 -> 7.85
A113: 06/03/2026 | B113: 4806502720172 | C113: 0-144160 | D113: GAR BUTTER TOAST 2-SLICE PACK 50G | E113: 1 | F113: 16.91 | G113: 18.6 | H113: =E113*G113 -> 18.6 | J113: 0 | K113: =H113+I113-J113 -> 18.6 | L113: =E113*F113 -> 16.91
A114: 06/03/2026 | B114: 4800361410816 | C114: 0-144160 | D114: NESTLE BEARBRAND SWAK PACK 33G | E114: 1 | F114: 10.64 | G114: 12.25 | H114: =E114*G114 -> 12.25 | J114: 0 | K114: =H114+I114-J114 -> 12.25 | L114: =E114*F114 -> 10.64
A115: 06/03/2026 | B115: 8998666001726 | C115: 0-144160 | D115: KOPIKO BLANCA TWINPACK 52G | E115: 1 | F115: 12.66 | G115: 14.25 | H115: =E115*G115 -> 14.25 | J115: 0 | K115: =H115+I115-J115 -> 14.25 | L115: =E115*F115 -> 12.66
... A144: 06/04/2026 | B144: 4800361393669 | C144: 0-144174 | D144: NESCAFE CLASSIC 200G | E144: 1 | F144: 200.03 | G144: 230 | H144: =E144*G144 -> 230 | J144: 0 | K144: =H144+I144-J144 -> 230 | L144: =E144*F144 -> 200.03
A145: 06/04/2026 | B145: 888123456781555 | C145: 0-144174 | D145: VICTORIA WASH SUGAR 1/2 | E145: 2 | G145: 37 | H145: =E145*G145 -> 74 | J145: 0 | K145: =H145+I145-J145 -> 74 | L145: =E145*F145 -> 0
A146: 06/04/2026 | B146: 00013 | C146: 0-144178 | D146: CONVIE SPRITE 1.5 | E146: 6 | F146: 59.58 | G146: 67.5 | H146: =E146*G146 -> 405 | J146: 0 | K146: =H146+I146-J146 -> 405 | L146: =E146*F146 -> 357.48
A147: 06/04/2026 | B147: 750515030206 | C147: 0-144178 | D147: SKYFLAKES GARLIC 10S 250G | E147: 1 | F147: 60.25 | G147: 69.5 | H147: =E147*G147 -> 69.5 | J147: 0 | K147: =H147+I147-J147 -> 69.5 | L147: =E147*F147 -> 60.25
A148: 06/04/2026 | B148: 4807770100697 | C148: 0-144178 | D148: BINGO VANILLA 280G | E148: 1 | F148: 59.5 | G148: 68.5 | H148: =E148*G148 -> 68.5 | J148: 0 | K148: =H148+I148-J148 -> 68.5 | L148: =E148*F148 -> 59.5
A149: 06/04/2026 | B149: 4807770100611 | C149: 0-144178 | D149: BINGO DOUBLE CHOCO 280G | E149: 1 | F149: 59.5 | G149: 68.5 | H149: =E149*G149 -> 68.5 | J149: 0 | K149: =H149+I149-J149 -> 68.5 | L149: =E149*F149 -> 59.5
A150: 06/04/2026 | B150: 4808647010033 | C150: 0-144178 | D150: CHEEZ WHIZ ORIGINAL 440G | E150: 1 | F150: 178.1 | G150: 205 | H150: =E150*G150 -> 205 | J150: 0 | K150: =H150+I150-J150 -> 205 | L150: =E150*F150 -> 178.1
A151: 06/04/2026 | B151: 4800888602268 | C151: 0-144178 | D151: LADYS CHOICE REAL MAYONNAISE DOYPACK 220ML | E151: 1 | F151: 89.91 | G151: 103.5 | H151: =E151*G151 -> 103.5 | J151: 0 | K151: =H151+I151-J151 -> 103.5 | L151: =E151*F151 -> 89.91
A152: 06/04/2026 | B152: 4800116043023 | C152: 0-144178 | D152: BUTTER CREAM CRACKERS 10X25G | E152: 1 | F152: 60.75 | G152: 67.25 | H152: =E152*G152 -> 67.25 | J152: 0 | K152: =H152+I152-J152 -> 67.25 | L152: =E152*F152 -> 60.75
A153: 06/04/2026 | B153: 8998389124184 | C153: 0-144178 | D153: KUKIS KELAPA COCONUT 60G | E153: 1 | F153: 12.77 | G153: 14.75 | H153: =E153*G153 -> 14.75 | J153: 0 | K153: =H153+I153-J153 -> 14.75 | L153: =E153*F153 -> 12.77
A154: 06/04/2026 | B154: 4800016642029 | C154: 0-144180 | D154: CHIPPY BBQ FLAVOR 27G | E154: 1 | F154: 6.83 | G154: 9.75 | H154: =E154*G154 -> 9.75 | J154: 0 | K154: =H154+I154-J154 -> 9.75 | L154: =E154*F154 -> 6.83
A155: 06/04/2026 | B155: 4807770122903 | C155: 0-144181 | D155: MONDE BANANA BAR 10X20G | E155: 1 | F155: 85.25 | G155: 98.25 | H155: =E155*G155 -> 98.25 | J155: 0 | K155: =H155+I155-J155 -> 98.25 | L155: =E155*F155 -> 85.25
A156: 06/04/2026 | B156: 4800552888080 | C156: 0-144182 | D156: CHIPS DELIGHT PARTY PACK COOKIES 130G | E156: 1 | F156: 54.05 | G156: 63 | H156: =E156*G156 -> 63 | J156: 0 | K156: =H156+I156-J156 -> 63 | L156: =E156*F156 -> 54.05
A157: 06/04/2026 | B157: 4800361331500 | C157: 0-144183 | D157: NESTLE BEARBRAND STERILIZED 200ML | E157: 1 | F157: 23.13 | G157: 30.25 | H157: =E157*G157 -> 30.25 | J157: 0 | K157: =H157+I157-J157 -> 30.25 | L157: =E157*F157 -> 23.13
... A269: 06/07/2026 | B269: 4806518846040 | C269: 0-144289 | D269: HONEY HOUSE MINI 30X10S 25G | E269: 1 | F269: 57.4 | G269: 66 | H269: =E269*G269 -> 66 | J269: 0 | K269: =H269+I269-J269 -> 66 | L269: =E269*F269 -> 57.4
A270: 06/07/2026 | B270: 750515018501 | C270: 0-144289 | D270: SKYFLAKES CRACKERS 25GX10S | E270: 1 | G270: 73.25 | H270: =E270*G270 -> 73.25 | J270: 0 | K270: =H270+I270-J270 -> 73.25 | L270: =E270*F270 -> 0
A271: 06/07/2026 | B271: 4800086050267 | C271: 0-144289 | D271: SEL ORANGE BLAST 45ML | E271: 1 | F271: 9.28 | G271: 10.75 | H271: =E271*G271 -> 10.75 | J271: 0 | K271: =H271+I271-J271 -> 10.75 | L271: =E271*F271 -> 9.28
A272: 06/07/2026 | B272: 4800016661006 | C272: 0-144289 | D272: ROLLER COASTER CHEDDAR CHEESE 24G | E272: 2 | F272: 7.06 | G272: 8.25 | H272: =E272*G272 -> 16.5 | J272: 0 | K272: =H272+I272-J272 -> 16.5 | L272: =E272*F272 -> 14.12
A273: 06/07/2026 | B273: 4800086043306 | C273: 0-144289 | D273: SEL CORNETTO COOKIES & DREAM 110ML | E273: 1 | F273: 20.4 | G273: 24 | H273: =E273*G273 -> 24 | J273: 0 | K273: =H273+I273-J273 -> 24 | L273: =E273*F273 -> 20.4
A274: 06/07/2026 | B274: 4800086046987 | C274: 0-144289 | D274: SEL CREAMDAE CUPS CHOCO 100ML | E274: 1 | F274: 18.56 | G274: 21.5 | H274: =E274*G274 -> 21.5 | J274: 0 | K274: =H274+I274-J274 -> 21.5 | L274: =E274*F274 -> 18.56
A275: 06/07/2026 | B275: 4809011681392 | C275: 0-144289 | D275: BOY BAWANG CHILI CHEESE 100G | E275: 1 | F275: 16.03 | G275: 18.5 | H275: =E275*G275 -> 18.5 | J275: 0 | K275: =H275+I275-J275 -> 18.5 | L275: =E275*F275 -> 16.03
A276: 06/07/2026 | B276: 4806505854225 | C276: 0-144289 | D276: CHICK BOY CHEESE FLAVOR 100G | E276: 1 | F276: 17.65 | G276: 20.5 | H276: =E276*G276 -> 20.5 | J276: 0 | K276: =H276+I276-J276 -> 20.5 | L276: =E276*F276 -> 17.65
A277: 06/07/2026 | B277: 4801668100264 | C277: 0-144289 | D277: MANG TOMAS ALL AROUND SARSA 325G | E277: 1 | F277: 35 | G277: 41.25 | H277: =E277*G277 -> 41.25 | J277: 0 | K277: =H277+I277-J277 -> 41.25 | L277: =E277*F277 -> 35
A278: 06/07/2026 | B278: 4800024581105 | C278: 0-144289 | D278: DM JUICE DRINK PINEAPPLE ACE 6S | E278: 1 | F278: 27.66 | G278: 32 | H278: =E278*G278 -> 32 | J278: 0 | K278: =H278+I278-J278 -> 32 | L278: =E278*F278 -> 27.66
A279: 06/07/2026 | B279: 7622300858575 | C279: 0-144291 | D279: TANG DALANDAN 25G | E279: 2 | F279: 18.2 | G279: 21 | H279: =E279*G279 -> 42 | J279: 0 | K279: =H279+I279-J279 -> 42 | L279: =E279*F279 -> 36.4
A280: 06/07/2026 | B280: 4800119221091 | C280: 0-144297 | D280: SKIN WHITE WHITENING LOTION PAPAYA MILK SPF 10 100ML | E280: 1 | F280: 71.3 | G280: 82 | H280: =E280*G280 -> 82 | J280: 0 | K280: =H280+I280-J280 -> 82 | L280: =E280*F280 -> 71.3
A281: 06/07/2026 | B281: 4809013300215 | C281: 0-144297 | D281: KOJIE SAN SKIN LIGHTENING SOAP CLASSIC 65G | E281: 1 | F281: 62.45 | G281: 72 | H281: =E281*G281 -> 72 | J281: 0 | K281: =H281+I281-J281 -> 72 | L281: =E281*F281 -> 62.45
A282: 06/07/2026 | B282: 888123456781858 | C282: 0-144297 | D282: OTC DYNAMITE MELON MINT RETAIL | E282: 1 | F282: 0.76 | G282: 1 | H282: =E282*G282 -> 1 | J282: 0 | K282: =H282+I282-J282 -> 1 | L282: =E282*F282 -> 0.76
... A361: 06/09/2026 | B361: 8886001038011 | C361: 0-144376 | D361: BENGBENG 26.5G | E361: 1 | F361: 6.67 | G361: 9.5 | H361: =E361*G361 -> 9.5 | J361: 0 | K361: =H361+I361-J361 -> 9.5 | L361: =E361*F361 -> 6.67
A362: 46183 | B362: 8410028902477 | C362: 0-144378 | D362: ALFONSO I LIGHT 500ML 25%VOL | E362: 5 | F362: 137.75 | G362: 158.5 | H362: =E362*G362 -> 792.5 | J362: 0 | K362: =H362+I362-J362 -> 792.5 | L362: =E362*F362 -> 688.75
A363: 46183 | B363: 8410162100234 | C363: 0-144378 | D363: FUNDADOR LIGHT 1L | E363: 1 | F363: 355 | G363: 408.25 | H363: =E363*G363 -> 408.25 | J363: 0 | K363: =H363+I363-J363 -> 408.25 | L363: =E363*F363 -> 355
A364: 46183 | B364: 8410028900091 | C364: 0-144378 | D364: ALFONSO I LIGHT 1L 25%VOL | E364: 1 | F364: 273 | G364: 314 | H364: =E364*G364 -> 314 | J364: 0 | K364: =H364+I364-J364 -> 314 | L364: =E364*F364 -> 273
A365: 46183 | B365: 4806502721452 | C365: 0-144379 | D365: GAR HIGH FIBER WHEAT BREAD 400G | E365: 1 | F365: 72.95 | G365: 80.25 | H365: =E365*G365 -> 80.25 | J365: 0 | K365: =H365+I365-J365 -> 80.25 | L365: =E365*F365 -> 72.95
A366: 46183 | B366: 4800024556165 | C366: 0-144380 | D366: DM ORIGINAL STYLE TOMATO SAUCE 900G | E366: 1 | F366: 90.24 | G366: 103.75 | H366: =E366*G366 -> 103.75 | J366: 0 | K366: =H366+I366-J366 -> 103.75 | L366: =E366*F366 -> 90.24
A367: 46183 | B367: 4800024583178 | C367: 0-144381 | D367: DEL POTATO CRISP BISCUITS SPICY 50G | E367: 1 | F367: 20.68 | G367: 24 | H367: =E367*G367 -> 24 | J367: 0 | K367: =H367+I367-J367 -> 24 | L367: =E367*F367 -> 20.68
A368: 46183 | B368: 888123456781858 | C368: 0-144382 | D368: OTC DYNAMITE MELON MINT RETAIL | E368: 5 | F368: 0.76 | G368: 1 | H368: =E368*G368 -> 5 | J368: 0 | K368: =H368+I368-J368 -> 5 | L368: =E368*F368 -> 3.8
A369: 46183 | B369: 4800130100016 | C369: 0-144384 | D369: GINEBRA SAN MIGUEL 4X4 700ML | E369: 1 | F369: 129 | G369: 148.5 | H369: =E369*G369 -> 148.5 | J369: 0 | K369: =H369+I369-J369 -> 148.5 | L369: =E369*F369 -> 129
A370: 46183 | B370: 750515031067 | C370: 0-144385 | D370: OTC SKYFLAKES SWEET BUTTER 30G | E370: 2 | F370: 6.4 | G370: 7.5 | H370: =E370*G370 -> 15 | J370: 0 | K370: =H370+I370-J370 -> 15 | L370: =E370*F370 -> 12.8
A371: 46183 | B371: 4800361415347 | C371: 0-144385 | D371: NESCAFE ORIGINAL TWIN PACK 56G | E371: 1 | F371: 13.32 | G371: 15.5 | H371: =E371*G371 -> 15.5 | J371: 0 | K371: =H371+I371-J371 -> 15.5 | L371: =E371*F371 -> 13.32
A372: 46183 | B372: 4800010075922 | C372: 0-144386 | D372: PRESTO CREAMS PEANUT BUTTER 300G | E372: 1 | F372: 59.51 | G372: 68.5 | H372: =E372*G372 -> 68.5 | J372: 0 | K372: =H372+I372-J372 -> 68.5 | L372: =E372*F372 -> 59.51
A373: 46183 | B373: 4806506311079 | C373: 0-144388 | D373: SISTERS SULIT SAVINGS PACK | E373: 1 | F373: 47.5 | G373: 54.75 | H373: =E373*G373 -> 54.75 | J373: 0 | K373: =H373+I373-J373 -> 54.75 | L373: =E373*F373 -> 47.5
... A411: 46183 | B411: 8850006325216 | C411: 0-144418 | D411: COLGATE ORIGINAL TWINPACK 24G | E411: 2 | F411: 8.3 | G411: 9.75 | H411: =E411*G411 -> 19.5 | J411: 0 | K411: =H411+I411-J411 -> 19.5 | L411: =E411*F411 -> 16.6
A412: 06/11/2026 | B412: 4800086049230 | C412: 0-144419 | D412: SEL CREAMDAE CUPS MANGO 100ML | E412: 1 | F412: 18.2 | G412: 21 | H412: =E412*G412 -> 21 | J412: 0 | K412: =H412+I412-J412 -> 21 | L412: =E412*F412 -> 18.2
A413: 06/11/2026 | B413: 4800086043306 | C413: 0-144419 | D413: SEL CORNETTO COOKIES & DREAM 110ML | E413: 1 | F413: 20.4 | G413: 24 | H413: =E413*G413 -> 24 | J413: 0 | K413: =H413+I413-J413 -> 24 | L413: =E413*F413 -> 20.4
A414: 06/11/2026 | B414: 4800047841705 | C414: 0-144419 | D414: ZONROX COLORSAFE BLEACH BLOSSOM FRESH 900ML | E414: 1 | F414: 65.99 | G414: 76.75 | H414: =E414*G414 -> 76.75 | J414: 0 | K414: =H414+I414-J414 -> 76.75 | L414: =E414*F414 -> 65.99
A415: 06/11/2026 | B415: 4805885171007 | C415: 0-144420 | D415: RENO LIVER SPREAD 85G | E415: 1 | F415: 29.95 | G415: 34.5 | H415: =E415*G415 -> 34.5 | J415: 0 | K415: =H415+I415-J415 -> 34.5 | L415: =E415*F415 -> 29.95
A416: 06/11/2026 | B416: 4806506311079 | C416: 0-144421 | D416: SISTERS SULIT SAVINGS PACK | E416: 2 | F416: 47.5 | G416: 54.75 | H416: =E416*G416 -> 109.5 | J416: 0 | K416: =H416+I416-J416 -> 109.5 | L416: =E416*F416 -> 95
A417: 06/11/2026 | B417: 4806502720615 | C417: 0-144421 | D417: GAR CLASSIC WHITE BREAD 600G REGULAR SLICE | E417: 1 | F417: 84.8 | G417: 94 | H417: =E417*G417 -> 94 | J417: 0 | K417: =H417+I417-J417 -> 94 | L417: =E417*F417 -> 84.8
A418: 06/11/2026 | B418: 4800361388252 | C418: 0-144421 | D418: NESCAFE CLASSIC 1.9GX48 | E418: 1 | F418: 145.18 | G418: 167 | H418: =E418*G418 -> 167 | J418: 0 | K418: =H418+I418-J418 -> 167 | L418: =E418*F418 -> 145.18
A419: 06/11/2026 | B419: 4800130100030 | C419: 0-144422 | D419: GINEBRA SAN MIGUEL 2X2 350ML | E419: 1 | F419: 68 | G419: 78.25 | H419: =E419*G419 -> 78.25 | J419: 0 | K419: =H419+I419-J419 -> 78.25 | L419: =E419*F419 -> 68
A420: 06/11/2026 | B420: 4800130100016 | C420: 0-144423 | D420: GINEBRA SAN MIGUEL 4X4 700ML | E420: 1 | F420: 129 | G420: 148.5 | H420: =E420*G420 -> 148.5 | J420: 0 | K420: =H420+I420-J420 -> 148.5 | L420: =E420*F420 -> 129
A421: 06/11/2026 | B421: 48025522 | C421: 0-144424 | D421: MAGGI MAGIC SARAP 8G | E421: 16 | F421: 4.74 | G421: 5.5 | H421: =E421*G421 -> 88 | J421: 0 | K421: =H421+I421-J421 -> 88 | L421: =E421*F421 -> 75.84
A422: 06/11/2026 | B422: 4806517042085 | C422: 0-144425 | D422: GOYA BAR DARK CHOCOLATE 30G | E422: 2 | F422: 23.63 | G422: 27.25 | H422: =E422*G422 -> 54.5 | J422: 0 | K422: =H422+I422-J422 -> 54.5 | L422: =E422*F422 -> 47.26
A423: 06/11/2026 | B423: 750515031067 | C423: 0-144426 | D423: OTC SKYFLAKES SWEET BUTTER 30G | E423: 1 | F423: 6.4 | G423: 7.5 | H423: =E423*G423 -> 7.5 | J423: 0 | K423: =H423+I423-J423 -> 7.5 | L423: =E423*F423 -> 6.4
... A613: 06/15/2026 | B613: 4800888602725 | C613: 0-144580 | D613: KNORR PORK BROTH CUBE 10G | E613: 24 | F613: 6.02 | G613: 7.25 | H613: =E613*G613 -> 174 | J613: 0 | K613: =H613+I613-J613 -> 174 | L613: =E613*F613 -> 144.48
A614: 46189 | B614: 8998666001726 | C614: 0-144586 | D614: KOPIKO BLANCA TWINPACK 52G | E614: 5 | F614: 12.66 | G614: 14.25 | H614: =E614*G614 -> 71.25 | J614: 0 | K614: =H614+I614-J614 -> 71.25 | L614: =E614*F614 -> 63.3
A615: 46189 | B615: 4800361382083 | C615: 0-144586 | D615: NESTEA APPLE BLACK TEA 25G | E615: 2 | F615: 18.57 | G615: 21.5 | H615: =E615*G615 -> 43 | J615: 0 | K615: =H615+I615-J615 -> 43 | L615: =E615*F615 -> 37.14
...

Sheet VARIANCE-checking
A1: SHORT
A2: SHELF NO. | B2: BARCODE | C2: PRODUCT NAME | D2: UNIT COST | E2: Actual Count May 2026 | F2: PURCHASES/ RETAIL | G2: PULL OUT | H2: SALES | I2: TOTAL | J2: ACTUAL INVENTORY | K2: VARIANCE - QUANTITY | L2: VARIANCE - COST | M2: REMARKS / CAUSE OF VARIANCE
A3: 1 | B3: 4809011681095 | C3: BOY BAWANG CORNICK ADOBO 100G | D3: 16.03 | E3: 17 | H3: 4 | I3: 13 | J3: 12 | K3: 1 | L3: 16.03
A4: 1 | B4: 4809011681507 | C4: BOY BAWANG CORNICK BBQ FLAVOR 100G | D4: 16.03 | E4: 70 | H4: 4 | I4: 66 | J4: 65 | K4: 1 | L4: 16.03
A5: 1 | B5: 4800631000488 | C5: BOY BAWANG MIXED NUTS GARLIC FLAVOR 100G | D5: 32.13 | E5: 36 | H5: 6 | I5: 30 | J5: 16 | K5: 14 | L5: 449.82 | M5: 1-Expired 4/15/2025
A6: 1 | B6: 4800016110542 | C6: CHICHARRON NI MANG JUAN SUKAT SILI 26G | D6: 6.83 | E6: 33 | H6: 3 | I6: 30 | J6: 29 | K6: 1 | L6: 6.83
A7: 1 | B7: 4800216120013 | C7: CLOVER CHEESE 24G | D7: 7.51 | E7: 94 | H7: 8 | I7: 86 | J7: 84 | K7: 2 | L7: 15.02 | M7: 20-EXPIRED 8/21/2024
A8: 1 | B8: 4800216126800 | C8: CLOVER CHIPS CHILI&CHEESE 55G | D8: 21.34 | E8: 7 | I8: 7 | J8: 5 | K8: 2 | L8: 42.68 | M8: 45903
A9: 1 | B9: 4800194116114 | C9: CORN OLE BARBECUE FLAVOR 22G | D9: 6.18 | E9: 228 | I9: 228 | J9: 73 | K9: 155 | L9: 957.9
A10: 1 | B10: 4800054111280 | C10: GROWERS GARLIC FLAVOR PEANUTS 80G | D10: 34.38 | E10: 5 | H10: 2 | I10: 3 | J10: 2 | K10: 1 | L10: 34.38
A11: 1 | B11: 4800054123283 | C11: GROWERS MIX NUTS 80G | D11: 61.5 | E11: 19 | H11: 3 | I11: 16 | J11: 15 | K11: 1 | L11: 61.5
A12: 1 | B12: 4800054121227 | C12: GROWERS SALTED CASHEW NUTS | D12: 30.77 | E12: 25 | I12: 25 | K12: 25 | L12: 769.25
A13: 1 | B13: 4800054125287 | C13: GROWERS SALTED PISTACHIO NUTS 80G | D13: 114.79 | E13: 22 | I13: 22 | J13: 21 | K13: 1 | L13: 114.79
A14: 1 | B14: 4800054112287 | C14: GROWERS SAVOURY HOT PEANUTS 80G | D14: 36.58 | E14: 22 | H14: 1 | I14: 21 | K14: 21 | L14: 768.18
A15: 1 | B15: 4800054122224 | C15: GROWERS TOASTED CASHEW NUTS 28G | D15: 30.77 | E15: 9 | I15: 9 | K15: 9 | L15: 276.93
A16: 1 | B16: 4800016680540 | C16: HONEY BUTTER POTATO CHIPS 22G | D16: 16.58 | E16: 18 | F16: 80 | H16: 3 | I16: 95 | J16: 94 | K16: 1 | L16: 16.58
A17: 1 | B17: 4800016680267 | C17: HONEY BUTTER POTATO CHIPS 60G | D17: 39.48 | E17: 23 | H17: 8 | I17: 15 | K17: 15 | L17: 592.2
A18: 1 | B18: 4800361028639 | C18: NESTLE KOKO KRUNCH 20G | D18: 11.78 | E18: 1 | I18: 1 | K18: 1 | L18: 11.78
A19: 1 | B19: 4800194177962 | C19: OISHI PRAWN CRACKERS SPICY FLAVOR 90G | D19: 21.97 | E19: 17 | I19: 17 | J19: 16 | K19: 1 | L19: 21.97 | M19: 15-expired 5/2026
A20: 1 | B20: 4800016603259 | C20: VCUT CHEESE 25G | D20: 15.65 | E20: 129 | H20: 1 | I20: 128 | J20: 75 | K20: 53 | L20: 829.45 | M20: 23-EXPIRED 11/24/2025
A21: 2 | B21: 4800220608750 | C21: EMBASSY PREMIUM BLENDED WHISKY 750ML | D21: 147.75 | E21: 3 | I21: 3 | K21: 3 | L21: 443.25
A22: 2 | B22: 8410028901289 | C22: VINO FONTANA SWEET RED 750ML | D22: 239.94 | E22: 7 | I22: 7 | K22: 7 | L22: 1679.58
A23: 3 | B23: 4807770100611 | C23: BINGO DOUBLE CHOCO 280G | D23: 57.25 | E23: 7 | H23: 2 | I23: 5 | J23: 1 | K23: 4 | L23: 229
A24: 3 | B24: 4800194173223 | C24: BREAD PAN CHEESE&ONION 42G | D24: 10.75 | E24: 50 | I24: 50 | K24: 50 | L24: 537.5
A25: 3 | B25: 4800116099020 | C25: BUTTER CREAM ENSAYMADA CRACKERS 10X25G | D25: 58.45 | E25: 11 | G25: 1 | H25: 1 | I25: 9 | J25: 8 | K25: 1 | L25: 58.45
A26: 3 | B26: 4800552888059 | C26: CHIPS DELIGHT CHOCOLATE CHIP COOKIES 80G | D26: 30.04 | E26: 11 | H26: 2 | I26: 9 | J26: 8 | K26: 1 | L26: 30.04
A27: 3 | B27: 4800016627262 | C27: CHOCO KNOTS CHOCOLATE 28G | D27: 7.48 | E27: 10 | F27: 25 | G27: 8 | H27: 3 | I27: 24 | J27: 22 | K27: 2 | L27: 14.96
A28: 3 | B28: 4806502726532 | C28: GAR BANANA CHOCO MUFFIN 45G | D28: 22.85 | E28: 6 | H28: 1 | I28: 5 | K28: 5 | L28: 114.25
A29: 3 | B29: 4806502726129 | C29: GAR CHEESE BUNS 250G | D29: 65 | E29: 1 | F29: 4 | H29: 2 | I29: 3 | J29: 1 | K29: 2 | L29: 130
A30: 3 | B30: 4806502720301 | C30: GAR HIGH FIBER WHEAT BREAD 600G | D30: 100 | E30: 2 | F30: 3 | H30: 2 | I30: 3 | K30: 3 | L30: 300
A31: 3 | B31: 4806502725894 | C31: GAR HIGH FIBER WHEAT RAISIN LOAF 400G | D31: 89.1 | E31: 2 | I31: 2 | K31: 2 | L31: 178.2
A32: 3 | B32: 4806502725900 | C32: GAR HIGH FIBER WHEAT RAISIN LOAF 600G | D32: 113.65 | E32: 1 | I32: 1 | K32: 1 | L32: 113.65
A33: 3 | B33: 4806502725900 | C33: GAR HIGH FIBER WHEAT RAISIN LOAF 600G | D33: 125 | E33: 1 | I33: 1 | K33: 1 | L33: 125
A34: 3 | B34: 4806502726907 | C34: GAR NEUBAKE CLASSIC WHITE BREAD SUPER SLICE 300G | D34: 41.15 | E34: 1 | F34: 2 | G34: 2 | I34: 1 | K34: 1 | L34: 41.15
A35: 3 | B35: 4806502726822 | C35: GAR NEUBAKE WHITE BREAD 450G | D35: 53.9 | E35: 2 | F35: 5 | G35: 3 | H35: 2 | I35: 2 | J35: 1 | K35: 1 | L35: 53.9
A36: 3 | B36: 8850338005206 | C36: HALLS FRESH LIME 140G | D36: 41.46 | E36: 1 | I36: 1 | K36: 1 | L36: 41.46
A37: 3 | B37: 4800016079559 | C37: HELLO CHOCO COATED WAFER SANDWICH 15GX10 | D37: 49.65 | E37: 2 | I37: 2 | K37: 2 | L37: 99.3
A38: 3 | B38: 8998389124184 | C38: KUKIS KELAPA COCONUT 60G | D38: 12.77 | E38: 10 | H38: 9 | I38: 1 | K38: 1 | L38: 12.77
A39: 3 | B39: 4800016087622 | C39: MAGIC CREAM BUTTER | D39: 53.87 | E39: 2 | I39: 2 | K39: 2 | L39: 107.74
A40: 3 | B40: 4800016628283 | C40: MINI CHOCO PRETZELS 28G | D40: 7.41 | E40: 3 | F40: 25 | G40: 4 | H40: 8 | I40: 16 | J40: 3 | K40: 13 | L40: 96.33
A41: 3 | B41: 4807770121661 | C41: MONDE SPECIAL MAMON CLASSIC SAVER PACK 12X43G | D41: 177.9 | E41: 4 | F41: 3 | G41: 1 | H41: 1 | I41: 5 | J41: 4 | K41: 1 | L41: 177.9
A42: 3 | B42: 4807770100703 | C42: NISSIN BREAD STIX 20G | D42: 5.68 | E42: 1 | I42: 1 | K42: 1 | L42: 5.68 | M42: 1-Expired 6/16/2025
A43: 3 | B43: 4807770101502 | C43: NISSIN BREADSTIX 20G PACK | D43: 58.8 | E43: 6 | I43: 6 | K43: 6 | L43: 352.8
A44: 3 | B44: 4807770121203 | C44: NISSIN CHOCO WAFER STICK 280G | D44: 59.5 | E44: 2 | I44: 2 | K44: 2 | L44: 119
A45: 3 | B45: 4807770121227 | C45: NISSIN STRAWBERRY STICK WAFER 280G | D45: 59.5 | E45: 7 | I45: 7 | K45: 7 | L45: 416.5
A46: 3 | B46: 8992760223046 | C46: OREO CHOCOLATE CREME 12X28.5G | D46: 67.28 | E46: 1 | I46: 1 | K46: 1 | L46: 67.28
A47: 3 | B47: 4800818801778 | C47: PRETZEE STRAWBERRY 21 GRAMS | D47: 6.27 | E47: 3 | I47: 3 | K47: 3 | L47: 18.81
A48: 3 | B48: 8993175537131 | C48: RICHEESE WAFER 22G | D48: 55 | E48: 14 | I48: 14 | J48: 2 | K48: 12 | L48: 660 | M48: 45843
A49: 3 | B49: 8993175539906 | C49: RICHOCO CHOCOLATE CREAM WAFER 10X20G | D49: 55 | E49: 24 | I49: 24 | J49: 21 | K49: 3 | L49: 165 | M49: 45361
A50: 3 | B50: 750515030312 | C50: SKYFLAKES CHEESE10S 250G | D50: 60.25 | E50: 3 | I50: 3 | K50: 3 | L50: 180.75
A51: 3 | B51: 750515030206 | C51: SKYFLAKES GARLIC 10S 250G | D51: 60.25 | E51: 5 | G51: 2 | H51: 2 | I51: 1 | K51: 1 | L51: 60.25
A52: 3 | B52: 750515030251 | C52: SKYFLAKES ONION& CHIVES 10S | D52: 60.25 | E52: 3 | G52: 2 | I52: 1 | K52: 1 | L52: 60.25
A53: 3 | B53: 4800631003205 | C53: SNB CHOCO CHIP COOKIES 500G | D53: 123.9 | E53: 1 | I53: 1 | K53: 1 | L53: 123.9
A54: 3 | B54: 7622202046810 | C54: TIGER BITES CHOCOLATE 10X18G | D54: 56.37 | E54: 3 | I54: 3 | K54: 3 | L54: 169.11
A55: 4 | B55: 8886001038011 | C55: BENGBENG 26.5G | D55: 7.5 | E55: 171 | H55: 6 | I55: 165 | J55: 161 | K55: 4 | L55: 30 | M55: 161-EXPIRED 8/14/2024
A56: 4 | B56: 4800818809361 | C56: FRUTOS MINIBITS SOUR 10G | D56: 1.77 | E56: 2 | I56: 2 | K56: 2 | L56: 3.54
A57: 4 | B57: 4806533325254 | C57: GOYA TAKE IT 2F 2+1 | D57: 33.76 | E57: 1 | F57: 10 | I57: 11 | J57: 9 | K57: 2 | L57: 67.52
A58: 4 | B58: 8850338000553 | C58: HALLS HONEY LEMON 140G | D58: 41.46 | E58: 1 | I58: 1 | K58: 1 | L58: 41.46
A59: 4 | B59: 4800818902017 | C59: LUVLOV BUDDY BERRY MILK PACK 15PCSX15G | D59: 58.14 | E59: 2 | H59: 1 | I59: 1 | K59: 1 | L59: 58.14
A60: 4 | B60: 93682978 | C60: M&MS PEANUT 40G | D60: 50.88 | F60: 24 | H60: 1 | I60: 23 | J60: 22 | K60: 1 | L60: 50.88
A61: 4 | B61: 4800214061271 | C61: MENTOS MINT CANDY 50 PCS 135G | D61: 38 | E61: 6 | H61: 1 | I61: 5 | J61: 4 | K61: 1 | L61: 38 | M61: 1-EXPIRED 3/21/2025
A62: 4 | B62: 4800103344218 | C62: MR. BUKO | D62: 21.48 | E62: 2 | I62: 2 | J62: 1 | K62: 1 | L62: 21.48 | M62: 2-Expired 8/5/2025
A63: 4 | B63: 4800194107822 | C63: O PUFF CHOCOLATE FILLED MARSHMALLOWS 24PCS | D63: 23.97 | E63: 1 | I63: 1 | K63: 1 | L63: 23.97
A64: 4 | B64: 69025310 | C64: SNICKERS 20G | D64: 13.77 | E64: 6 | F64: 12 | I64: 18 | J64: 12 | K64: 6 | L64: 82.62
A65: 5 | B65: 4800575144590 | C65: ALASKA POWDERED MILK DRINK 300ML | D65: 99.12 | E65: 9 | I65: 9 | K65: 9 | L65: 892.08
A66: 5 | B66: 8996001440049 | C66: ENERGEN CEREAL DRINK CHOCOLATE 40G | D66: 7.5 | E66: 240 | H66: 5 | I66: 235 | J66: 137 | K66: 98 | L66: 735 | M66: 277-Expired 3/12/2025
A67: 5 | B67: 8996001603444 | C67: ENERGEN CHAMPION TWINPACK 70G | D67: 14.37 | E67: 61 | I67: 61 | K67: 61 | L67: 876.57 | M67: 45672
A68: 5 | B68: 4800016022258 | C68: GREAT TASTE CHOCO TWIN PACK 50G | D68: 11.76 | E68: 251 | G68: 152 | I68: 99 | J68: 98 | K68: 1 | L68: 11.76
A69: 5 | B69: 4800016022180 | C69: GREAT TASTE WHITE CREMA TWINPACK 50G | D69: 11.39 | E69: 122 | G69: 120 | I69: 2 | K69: 2 | L69: 22.78 | M69: 120-EXPIRED 3/14/2024
A70: 5 | B70: 4806525940199 | C70: KINGS FINEST GLUTINOUS RICE FLOUR 500G | D70: 38.57 | E70: 20 | I70: 20 | J70: 16 | K70: 4 | L70: 154.28
A71: 5 | B71: 8998666001719 | C71: KOPIKO BROWN COFFEE TWINPACK 53G | D71: 11.5 | E71: 65 | H71: 12 | I71: 53 | J71: 47 | K71: 6 | L71: 69
A72: 5 | B72: 4809013526349 | C72: MR. GULAMAN YELLOW 25G | D72: 12.6 | E72: 22 | H72: 5 | I72: 17 | J72: 14 | K72: 3 | L72: 37.8 | M72: 13-Expired 5/16/2023
A73: 5 | B73: 888123456781526 | C73: MT. KALINGA GROUND COFFEE 400G | D73: 300 | E73: 17 | H73: 3 | I73: 14 | J73: 13 | K73: 1 | L73: 300
A74: 5 | B74: 4800361393683 | C74: NESCAFE CLASSIC RESEALABLE 100G | D74: 100.03 | E74: 26 | I74: 26 | K74: 26 | L74: 2600.78
A75: 5 | B75: 4800361423588 | C75: NESCAFE CREAMY WHITE SUGAR FREE TWIN PACK 11.2 GRAMS | D75: 13.21 | E75: 34 | H75: 2 | I75: 32 | K75: 32 | L75: 422.72
A76: 5 | B76: 4800361382083 | C76: NESTEA APPLE BLACK TEA 25G | D76: 18.57 | E76: 134 | H76: 10 | I76: 124 | J76: 120 | K76: 4 | L76: 74.28
A77: 5 | B77: 4800361379557 | C77: NESTEA LEMON BLACK TEA 25G | D77: 18.57 | E77: 6 | H77: 4 | I77: 2 | K77: 2 | L77: 37.14 | M77: 10-EXPIRED 7/31/2025
A78: 5 | B78: 4800361380737 | C78: NESTLE COFFEE MATE 450ML | D78: 109.57 | E78: 22 | H78: 11 | I78: 11 | J78: 10 | K78: 1 | L78: 109.57
A79: 5 | B79: 4800361423052 | C79: NESTLE LEMONADE CUCUMBER 200G | D79: 202 | E79: 7 | H79: 6 | I79: 1 | K79: 1 | L79: 202
A80: 5 | B80: 7622300638078 | C80: TANG STRAWBERRY 25G | D80: 17.81 | E80: 28 | I80: 28 | J80: 18 | K80: 10 | L80: 178.1 | M80: 44967
A81: 6 | B81: 4806500470857 | C81: DELICIOUS SULIT PLUS SPAGHETTI 800G | D81: 49.8 | E81: 5 | I81: 5 | J81: 2 | K81: 3 | L81: 149.4
A82: 6 | B82: 4800024575722 | C82: DM PARTY COMBO PCK SWEET STYLE | D82: 140 | E82: 1 | F82: 16 | H82: 7 | I82: 10 | J82: 9 | K82: 1 | L82: 140
A83: 6 | B83: 4806500473681 | C83: FAVORITO MACARONI 5KL | D83: 25.8 | E83: 17 | I83: 17 | J83: 11 | K83: 6 | L83: 154.8
A84: 6 | B84: 4806500472639 | C84: FAVORITO PANCIT CANTON 400G | D84: 48.6 | E84: 35 | H84: 31 | I84: 4 | K84: 4 | L84: 194.4
A85: 6 | B85: 4800528456374 | C85: HOBE SPECIAL PALABOK 454G | D85: 32 | E85: 159 | I85: 159 | J85: 146 | K85: 13 | L85: 416 | M85: 48-EXPIRED 5/2026
A86: 6 | B86: 089686170726 | C86: INDOMIE MI GORENG STIR FRIED ORIGINAL 85G | D86: 15.35 | E86: 47 | I86: 47 | K86: 47 | L86: 721.45
A87: 6 | B87: 4807770270017 | C87: LM BEEF NA BEEF 55G | D87: 8.75 | E87: 115 | H87: 1 | I87: 114 | J87: 75 | K87: 39 | L87: 341.25 | M87: 45709
A88: 6 | B88: 4807770272813 | C88: LM LA PAZ BATCHOY 55G | D88: 15 | E88: 13 | H88: 3 | I88: 10 | J88: 9 | K88: 1 | L88: 15
A89: 6 | B89: 4807770273674 | C89: LM PANCIT CANTON KALAMANSI 80G | D89: 14 | E89: 42 | I89: 42 | J89: 38 | K89: 4 | L89: 56
A90: 6 | B90: 4807770272097 | C90: LM SPICY BEEF 50G | D90: 10 | E90: 46 | I90: 46 | J90: 18 | K90: 28 | L90: 280 | M90: 18-EXPIRED 1/22/2025
A91: 6 | B91: 4806011812061 | C91: SUPER Q GOLDEN BIHON 454G | D91: 34 | E91: 1 | I91: 1 | K91: 1 | L91: 34
A92: 7 | B92: 4800575140158 | C92: ALASKA EVAPORADA CREAMER 140ML | D92: 19.06 | E92: 23 | H92: 2 | I92: 21 | J92: 10 | K92: 11 | L92: 209.66 | M92: 21-Expired Mar&June 2025
A93: 7 | B93: 4800575140370 | C93: ALASKA EVAPORADA CREAMER 360ML | D93: 35.15 | E93: 27 | H93: 9 | I93: 18 | J93: 17 | K93: 1 | L93: 35.15 | M93: 8-Expired 6/25/2025
A94: 7 | B94: 748485401225 | C94: ANGEL KREMDENSADA 410ML | D94: 59.55 | E94: 23 | H94: 2 | I94: 21 | J94: 20 | K94: 1 | L94: 59.55
A95: 7 | B95: 748485804057 | C95: ARGENTINA GINILING 100G | D95: 21.08 | E95: 35 | H95: 1 | I95: 34 | J95: 30 | K95: 4 | L95: 84.32
A96: 7 | B96: 748485800448 | C96: ARGENTINA MEAT LOAF 250G | D96: 32.8 | E96: 2 | I96: 2 | J96: 1 | K96: 1 | L96: 32.8
A97: 7 | B97: 4800249908237 | C97: CDO KARNE NORTE CLASSIC GUISADO 175G | D97: 31.13 | E97: 15 | I97: 15 | J97: 13 | K97: 2 | L97: 62.26
A98: 7 | B98: 4800249908725 | C98: CDO MEAT LOAF 100G | D98: 17.6 | E98: 12 | H98: 1 | I98: 11 | J98: 1 | K98: 10 | L98: 176
A99: 7 | B99: 748485100456 | C99: CENTURY TUNA CALDERETA 155G | D99: 34.48 | E99: 1 | I99: 1 | K99: 1 | L99: 34.48
A100: 7 | B100: 748485100081 | C100: CENTURY TUNA FLAKES IN OIL 180G | D100: 44.86 | E100: 11 | F100: 48 | H100: 11 | I100: 48 | J100: 44 | K100: 4 | L100: 179.44
...

Sheet KINALANGUYAN
A1: DATE | B1: PARTICULAR | C1: TRANSACTION NO: | D1: DESCRIPTION | E1: QTY. | F1: COST PRICE | G1: UNIT PRICE | H1: CASH SALE | I1: ACCOUNT RECEIVABLE | J1: SALES DISCOUNT | K1: NET SALES | L1: COGS
A2: 46190 | B2: 4800016012273 | C2: 0-144673 | D2: GREAT TASTE PREMIUM 50G | E2: 10 | F2: 47.73 | G2: 55 | I2: 550 | J2: 0 | K2: =H2+I2-J2 -> 550 | L2: =E2*F2 -> 477.3
A3: 46190 | B3: 4801668602034 | C3: 0-144673 | D3: DATU PUTI SOY SAUCE 200ML | E3: 15 | F3: 10 | G3: 12.5 | I3: 187.5 | J3: 0 | K3: =H3+I3-J3 -> 187.5 | L3: =E3*F3 -> 150
A4: 46190 | B4: 4800888285355 | C4: 0-144673 | D4: KNORR CHICKEN BROTH CUBE 10G 6+2 | E4: 3 | F4: 34.88 | G4: 40.25 | I4: 120.75 | J4: 0 | K4: =H4+I4-J4 -> 120.75 | L4: =E4*F4 -> 104.64
A5: 46190 | B5: 4800888607959 | C5: 0-144673 | D5: KNORR SHRIMP BROTH CUBE 10G | E5: 24 | F5: 6.02 | G5: 7.25 | I5: 174 | J5: 0 | K5: =H5+I5-J5 -> 174 | L5: =E5*F5 -> 144.48
A6: 46190 | B6: 4800888602725 | C6: 0-144673 | D6: KNORR PORK BROTH CUBE 10G | E6: 24 | F6: 6.02 | G6: 7.25 | I6: 174 | J6: 0 | K6: =H6+I6-J6 -> 174 | L6: =E6*F6 -> 144.48
A7: 46190 | B7: 4800888602732 | C7: 0-144673 | D7: KNORR BEEF BROTH CUBE 10G | E7: 24 | F7: 6.02 | G7: 7.25 | I7: 174 | J7: 0 | K7: =H7+I7-J7 -> 174 | L7: =E7*F7 -> 144.48
A8: 46190 | B8: 748485150079 | C8: 0-144673 | D8: COCO MAMA FRESH GATA 200ML | E8: 10 | F8: 32.86 | G8: 38 | I8: 380 | J8: 0 | K8: =H8+I8-J8 -> 380 | L8: =E8*F8 -> 328.6
A9: 46190 | B9: 748485150093 | C9: 0-144673 | D9: COCO MAMA FRESH GATA 400ML | E9: 6 | F9: 65.95 | G9: 76 | I9: 456 | J9: 0 | K9: =H9+I9-J9 -> 456 | L9: =E9*F9 -> 395.7
A10: 46190 | B10: 888123456781868 | C10: 0-144673 | D10: FAVORITO RIDGE&SHELL MACARONI 1/2 | E10: 10 | F10: 25.8 | G10: 29.75 | I10: 297.5 | J10: 0 | K10: =H10+I10-J10 -> 297.5 | L10: =E10*F10 -> 258
A11: 46190 | B11: 4800888207234 | C11: 0-144673 | D11: SUNSILK PINK (11+1) | E11: 5 | F11: 63.95 | G11: 73.75 | I11: 368.75 | J11: 0 | K11: =H11+I11-J11 -> 368.75 | L11: =E11*F11 -> 319.75
A12: 46190 | B12: 4800888194268 | C12: 0-144673 | D12: SUNSILK GREEN (11+1) | E12: 10 | F12: 63.95 | G12: 73.75 | I12: 737.5 | J12: 0 | K12: =H12+I12-J12 -> 737.5 | L12: =E12*F12 -> 639.5
A13: 46190 | B13: 4800528456282 | C13: 0-144673 | D13: HOBE BIHON 454G | E13: 12 | F13: 29.17 | G13: 33.75 | I13: 405 | J13: 0 | K13: =H13+I13-J13 -> 405 | L13: =E13*F13 -> 350.04
... A53: 46190 | B53: 750515017450 | C53: 0-144673 | D53: FITA CRACKERS 30GX10S | E53: 5 | F53: 56.5 | G53: 63 | I53: 315 | J53: 0 | K53: =H53+I53-J53 -> 315 | L53: =E53*F53 -> 282.5
A54: 46190 | B54: 750515018501 | C54: 0-144673 | D54: SKYFLAKES CRACKERS 25GX10S | E54: 5 | G54: 73.25 | I54: 366.25 | J54: 0 | K54: =H54+I54-J54 -> 366.25 | L54: =E54*F54 -> 0
A55: 46190 | B55: 4800818809880 | C55: 0-144673 | D55: VFRESH WINTER COOL GUM 165G | E55: 3 | F55: 34.27 | G55: 39.5 | I55: 118.5 | J55: 0 | K55: =H55+I55-J55 -> 118.5 | L55: =E55*F55 -> 102.81
A56: 46190 | B56: 4800818808302 | C56: 0-144673 | D56: FRUTOS ASSORTED SOFT CHEWY CANDIES 180G | E56: 2 | F56: 34.27 | G56: 39.5 | I56: 79 | J56: 0 | K56: =H56+I56-J56 -> 79 | L56: =E56*F56 -> 68.54
A57: 46190 | B57: 4800818810817 | C57: 0-144673 | D57: FRUTOS CHEWY SAMPALOK 175G | E57: 1 | F57: 34.27 | G57: 39.5 | I57: 39.5 | J57: 0 | K57: =H57+I57-J57 -> 39.5 | L57: =E57*F57 -> 34.27
A58: 46190 | B58: 4800818809712 | C58: 0-144673 | D58: CHAMPI CHOCOFILLED CHEWY CHOCOLATE CANDY 165G | E58: 3 | F58: 36.11 | G58: 41.75 | I58: 125.25 | J58: 0 | K58: =H58+I58-J58 -> 125.25 | L58: =E58*F58 -> 108.33
A59: 46190 | B59: 8935001727668 | C59: 0-144673 | D59: MENTOS MINT FLAVOR 50+5 PCS. | E59: 3 | F59: 38 | G59: 43.75 | I59: 131.25 | J59: 0 | K59: =H59+I59-J59 -> 131.25 | L59: =E59*F59 -> 114
A60: 46190 | B60: 4800016303081 | C60: 0-144673 | D60: MAXX DALANDAN ORANGE 200G | E60: 2 | F60: 38 | G60: 43.75 | I60: 87.5 | J60: 0 | K60: =H60+I60-J60 -> 87.5 | L60: =E60*F60 -> 76
A61: 46190 | B61: 4800016307010 | C61: 0-144673 | D61: MAXX EUCALYPTUS MENTHOL CANDY 200G | E61: 2 | F61: 38 | G61: 43.75 | I61: 87.5 | J61: 0 | K61: =H61+I61-J61 -> 87.5 | L61: =E61*F61 -> 76
A62: 46190 | B62: 4800818902017 | C62: 0-144673 | D62: LUVLOV BUDDY BERRY MILK PACK 15PCSX15G | E62: 1 | F62: 58.14 | G62: 67 | I62: 67 | J62: 0 | K62: =H62+I62-J62 -> 67 | L62: =E62*F62 -> 58.14
A63: 46190 | B63: 4800818809750 | C63: 0-144673 | D63: ICOOL MENTHOLATED GUM 182G | E63: 2 | F63: 34.27 | G63: 39.5 | I63: 79 | J63: 0 | K63: =H63+I63-J63 -> 79 | L63: =E63*F63 -> 68.54
A64: 46190 | B64: 8998666001726 | C64: 0-144673 | D64: KOPIKO BLANCA TWINPACK 52G | E64: 61 | F64: 12.66 | G64: 14.25 | I64: 869.25 | J64: 0 | K64: =H64+I64-J64 -> 869.25 | L64: =E64*F64 -> 772.26
A65: 46190 | B65: 748485401492 | C65: 0-144673 | D65: BIRCH TREE 33G | E65: 28 | F65: 7.85 | G65: 12 | I65: 336 | J65: 0 | K65: =H65+I65-J65 -> 336 | L65: =E65*F65 -> 219.8
A66: 46190 | B66: 4806505854416 | C66: 0-144673 | D66: CHICK BOY TEXAS SMOKED BBQ FLAVOR 100G | E66: 10 | F66: 17.65 | G66: 18.75 | I66: 187.5 | J66: 0 | K66: =H66+I66-J66 -> 187.5 | L66: =E66*F66 -> 176.5
... A113: 46190 | B113: 4800016012266 | C113: 0-144673 | D113: GREAT TASTE PREMIUM 25G | E113: 48 | F113: 24.35 | G113: 28 | I113: 1344 | J113: 0 | K113: =H113+I113-J113 -> 1344 | L113: =E113*F113 -> 1168.8
A114: 46190 | B114: 4800010012033 | C114: 0-144673 | D114: GREAT TASTE GRANULES 50G | E114: 2 | G114: 56.25 | I114: =E114*G114 -> 112.5 | J114: 0 | K114: =H114+I114-J114 -> 112.5 | L114: =E114*F114 -> 0
A115: 46190 | B115: 4800010012033 | C115: 0-144673 | D115: GREAT TASTE GRANULES 50G | E115: 4 | F115: 48.8 | G115: 56.25 | I115: =E115*G115 -> 225 | J115: 0 | K115: =H115+I115-J115 -> 225 | L115: =E115*F115 -> 195.2
A116: 46190 | B116: 4800016012280 | C116: 0-144673 | D116: GREAT TASTE PREMIUM 100G | E116: 10 | F116: 94.58 | G116: 109 | I116: 1090 | J116: 0 | K116: =H116+I116-J116 -> 1090 | L116: =E116*F116 -> 945.8
A117: 46190 | B117: 4800010012019 | C117: 0-144673 | D117: GREAT TASTE GRANULES 100G | E117: 6 | F117: 96.67 | G117: 111.25 | I117: 667.5 | J117: 0 | K117: =H117+I117-J117 -> 667.5 | L117: =E117*F117 -> 580.02
A118: 46190 | B118: 4807770271175 | C118: 0-144673 | D118: LM GO CUP BULALO 40G | E118: 3 | F118: 21.5 | G118: 24.75 | I118: 74.25 | J118: 0 | K118: =H118+I118-J118 -> 74.25 | L118: =E118*F118 -> 64.5
A119: 46190 | B119: 4807770273612 | C119: 0-144673 | D119: LM GO CUP SPICY BULALO 40G | E119: 2 | F119: 21.5 | G119: 24.75 | I119: 49.5 | J119: 0 | K119: =H119+I119-J119 -> 49.5 | L119: =E119*F119 -> 43
A120: 46190 | B120: 4807770271168 | C120: 0-144673 | D120: LM GO CUP BATCHOY 40G | E120: 3 | F120: 21.5 | G120: 24.75 | I120: 74.25 | J120: 0 | K120: =H120+I120-J120 -> 74.25 | L120: =E120*F120 -> 64.5
A121: 46190 | B121: 4807770273810 | C121: 0-144673 | D121: LM GO CUP SPICY BATCHOY 40G | E121: 3 | F121: 21.5 | G121: 24.75 | I121: 74.25 | J121: 0 | K121: =H121+I121-J121 -> 74.25 | L121: =E121*F121 -> 64.5
A122: 46190 | B122: 4800016561498 | C122: 0-144673 | D122: NISSIN CUP NOODLES CHEESY SEAFOOD 50G | E122: 6 | F122: 23.32 | G122: 27 | I122: 162 | J122: 0 | K122: =H122+I122-J122 -> 162 | L122: =E122*F122 -> 139.92
A123: 46190 | B123: 4800016561184 | C123: 0-144673 | D123: NISSIN CUP NOODLES CREAMY SEAFOOD 45G | E123: 6 | F123: 20.55 | G123: 23.75 | I123: 142.5 | J123: 0 | K123: =H123+I123-J123 -> 142.5 | L123: =E123*F123 -> 123.3
A124: 46190 | B124: 4800016551857 | C124: 0-144673 | D124: NISSIN CUP NOODLES SPICY SEAFOOD 40G | E124: 6 | F124: 21.17 | G124: 24.5 | I124: 147 | J124: 0 | K124: =H124+I124-J124 -> 147 | L124: =E124*F124 -> 127.02
A125: 46190 | B125: 4800016560927 | C125: 0-144673 | D125: NISSIN CUP NOODLES SPICY HOT BEEF 45G | E125: 6 | F125: 21.17 | G125: 24.5 | I125: 147 | J125: 0 | K125: =H125+I125-J125 -> 147 | L125: =E125*F125 -> 127.02
A126: 46190 | B126: 4800016552106 | C126: 0-144673 | D126: NISSIN CUP NOODLES BEEF 40G | E126: 6 | F126: 20.55 | G126: 23.75 | I126: 142.5 | J126: 0 | K126: =H126+I126-J126 -> 142.5 | L126: =E126*F126 -> 123.3
A127: 46190 | B127: 4805885172004 | C127: 0-144673 | D127: RENO LIVER SPREAD 230G | E127: 5 | F127: 61.5 | G127: 66.5 | I127: 332.5 | J127: 0 | K127: =H127+I127-J127 -> 332.5 | L127: =E127*F127 -> 307.5
... A155: 46190 | B155: 4808680020754 | C155: 0-144673 | D155: LADYS CHOICE SANDWICH SPREAD SACHET 80ML | E155: 6 | F155: 32.18 | G155: 41 | I155: 246 | J155: 4362.01 | K155: =H155+I155-J155 -> -4116.01 | L155: =E155*F155 -> 193.08

Sheet PURCHASES+
A1: PURCHASES
A2: =PRINTING!B2 -> AS OF JUNE 2026
A3: DATE | B3: PARTICULARS | C3: BARCODE | D3: CV No. | E3: DESCRIPTION | F3: QTY | G3: UNIT | H3: UNIT PRICE | I3: PURCHASES
A4: 46182 | B4: WING-AN MARKETING INC. | C4: 4801234107727 | D4: 2002 | E4: BAYGON MULTI INSECT KILLER ODORLESS 500ML | F4: 8 | G4: PC/S | H4: 360.65 | I4: =F4*H4 -> 2885.2
A5: 46182 | B5: WING-AN MARKETING INC. | C5: 4801234107826 | D5: 2002 | E5: BAYGON SHIELD PROTECTOR 500ML | F5: 8 | G5: PC/S | H5: 333.8 | I5: =F5*H5 -> 2670.4
A6: 46182 | B6: WING-AN MARKETING INC. | C6: 4800034017243 | D6: 2002 | E6: HAPEE EXPLOSIVE MENTHOL RED 55G | F6: 36 | G6: PC/S | H6: 10.95 | I6: =F6*H6 -> 394.2
A7: 46182 | B7: WING-AN MARKETING INC. | C7: 9780201379617 | D7: 2002 | E7: HOME RECIPE - PEANUT BUTTER 560G | F7: 16 | G7: PC/S | H7: 132.8 | I7: =F7*H7 -> 2124.8
A8: 46182 | B8: PROS MARKETING & PHARMAPLUS DRUGSTORE | C8: 4804888804868 | D8: 2003 | E8: MAMA SITAS OYSTER SAUCE 4.2KG | F8: 1 | G8: PC/S | H8: 723.8 | I8: =F8*H8 -> 723.8
A9: 46182 | B9: PROS MARKETING & PHARMAPLUS DRUGSTORE | C9: 4807770100536 | D9: 2003 | E9: BINGO ORANGE 280G | F9: 7 | G9: PC/S | H9: 59.5 | I9: =F9*H9 -> 416.5
A10: 46182 | B10: PROS MARKETING & PHARMAPLUS DRUGSTORE | C10: 4807770100963 | D10: 2003 | E10: NISSIN EGGNOG COOKIES 18G PACK | F10: 6 | G10: PC/S | H10: 58.8 | I10: =F10*H10 -> 352.8
A11: 46182 | B11: PROS MARKETING & PHARMAPLUS DRUGSTORE | C11: 4807770122712 | D11: 2003 | E11: MONDE CHOCO PUFF 240G | F11: 3 | G11: PC/S | H11: 81.5 | I11: =F11*H11 -> 244.5
A12: 46182 | B12: PROS MARKETING & PHARMAPLUS DRUGSTORE | C12: 4807770120770 | D12: 2003 | E12: SUMO MINI COOKIES&CREAM 10X20G | F12: 6 | G12: PC/S | H12: 58.95 | I12: =F12*H12 -> 353.7
A13: 46182 | B13: PROS MARKETING & PHARMAPLUS DRUGSTORE | C13: 4807770121661 | D13: 2003 | E13: MONDE SPECIAL MAMON CLASSIC SAVER PACK 12X43G | F13: 3 | G13: PC/S | H13: 177.9 | I13: =F13*H13 -> 533.7
A14: 46183 | B14: IBEST CORPORATION | C14: 4800024575722 | D14: 2004 | E14: DM PARTY COMBO PCK SWEET STYLE | F14: 16 | G14: PC/S | H14: 140 | I14: =F14*H14 -> 2240
A15: 46183 | B15: ACRO DISTRIBUTION AND LOGISTICS, INC. | C15: 4808680021805 | D15: 2005 | E15: LADYS CHOICE REAL MAYONNAISE 3.5L | F15: 4 | G15: PC/S | H15: 1160.3525 | I15: =F15*H15 -> 4641.41
... A44: 46184 | B44: CHIP ACCENDO ENTERPRISES INC. | C44: 4806533327128 | D44: 2007 | E44: DELFI TREASURES GOLDEN ALMOND 36G 2+1 | F44: 8 | G44: PC/S | H44: 109.965 | I44: =F44*H44 -> 879.72
A45: 46191 | B45: CYNTHIA CABRERA | C45: 999055 | D45: 2012 | E45: CONVIE SWIVEL CHAIR | F45: 4 | G45: PC/S | H45: 3500 | I45: =F45*H45 -> 14000
A46: 46191 | B46: PADSA ENTERPRISES CORPORATION | C46: 4806500802221 | D46: 2013 | E46: MAGIC PANTS PULL-UPS MEDIUM 10PCS | F46: 12 | G46: PACK/S | H46: 60.28 | I46: =F46*H46 -> 723.36
A47: 46191 | B47: PADSA ENTERPRISES CORPORATION | C47: 4806500802320 | D47: 2013 | E47: MAGIC PANTS PULL-UPS LARGE 10S | F47: 12 | G47: PACK/S | H47: 65.77 | I47: =F47*H47 -> 789.24
A48: 46191 | B48: PADSA ENTERPRISES CORPORATION | C48: 4806500802429 | D48: 2013 | E48: MAGIC PANTS PULL-UPS XL 10S | F48: 12 | G48: PACK/S | H48: 71.25 | I48: =F48*H48 -> 855
A49: 46191 | B49: PADSA ENTERPRISES CORPORATION | C49: 4806500802658 | D49: 2013 | E49: MAGIC PANTS DIAPERS PULL-UPS 30PCS-XXXL | F49: 4 | G49: PC/S | H49: 261.51 | I49: =F49*H49 -> 1046.04
A50: 46191 | B50: PADSA ENTERPRISES CORPORATION | C50: 4806500802252 | D50: 2013 | E50: MAGIC PANTS DIAPERS PULL-UPS 30PCS-MEDIUM | F50: 4 | G50: PC/S | H50: 180.86 | I50: =F50*H50 -> 723.44
A51: 46191 | B51: PADSA ENTERPRISES CORPORATION | C51: 4806500802351 | D51: 2013 | E51: MAGIC PANTS DIAPERS PULL-UPS 30PCS-LARGE | F51: 4 | G51: PC/S | H51: 197.3 | I51: =F51*H51 -> 789.2
A52: 46191 | B52: PADSA ENTERPRISES CORPORATION | C52: 4806500802450 | D52: 2013 | E52: MAGIC PANTS DIAPERS PULL-UPS 30S-XL | F52: 4 | G52: PC/S | H52: 213.74 | I52: =F52*H52 -> 854.96
A53: 46191 | B53: PADSA ENTERPRISES CORPORATION | C53: 4806500802559 | D53: 2013 | E53: MAGIC PANTS DIAPERS PULL-UPS 30PCS-XXL | F53: 4 | G53: PC/S | H53: 230.19 | I53: =F53*H53 -> 920.76
A54: 46191 | B54: PADSA ENTERPRISES CORPORATION | C54: 4806500802627 | D54: 2013 | E54: MAGIC PANTS PULL-UPS 10S-XXXL | F54: 12 | G54: PACK/S | H54: 87.17 | I54: =F54*H54 -> 1046.04
A55: 46191 | B55: PADSA ENTERPRISES CORPORATION | C55: 4806506150258 | D55: 2013 | E55: SOFT N WHITE EASY PACK 2PLY 40PULLS | F55: 24 | G55: PACK/S | H55: 8.75 | I55: =F55*H55 -> 210
A56: 46191 | B56: PADSA ENTERPRISES CORPORATION | C56: 4806506151118 | D56: 2013 | E56: SOFT N WHITE TRAVEL PACK 2PLY 50PULLS | F56: 24 | G56: PC/S | H56: 14.5 | I56: =F56*H56 -> 348
A57: 46192 | B57: AS-LS DISTRIBUTOR | C57: 4806502720615 | D57: 2016 | E57: GAR CLASSIC WHITE BREAD 600G REGULAR SLICE | F57: 3 | G57: PC/S | H57: 84.8 | I57: =F57*H57 -> 254.4
... A132: 46203 | B132: EDELIAS MARKETING | C132: 4806526070093 | D132: 2027 | E132: HELLO KITTY SOFT CANDY 30PCS | F132: 10 | G132: PC/S | H132: 25 | I132: =F132*H132 -> 250
F133: =SUM(F4:F132) -> 4042 | H133: =SUM(H4:H132) -> 15456.593 | I133: =SUM(I4:I132) -> 125669.26

Sheet RETAIL+
A1: RETAIL
A2: =PRINTING!B2 -> AS OF JUNE 2026
A3: DATE | B3: SUPPLIER | C3: BARCODE | D3: PARTICULAR | E3: QTY | F3: UNIT
A4: 46178 | B4: KIMBERLIN ENTERPRISES | C4: 888123456781258 | D4: OTC MAXX CHERRY | E4: 50 | F4: PCS
A5: 46178 | B5: KIMBERLIN ENTERPRISES | C5: 888123456781549 | D5: OTC DYNAMITE CHOCO MINT RETAIL | E5: 50 | F5: PCS
A6: 46178 | B6: PROS MARKETING & PHARMAPLUS DRUGSTORE | C6: 75051030176 | D6: OTC SKYFLAKES ONION & CHIVES | E6: 10 | F6: PCS
A7: 46178 | B7: PROS MARKETING & PHARMAPLUS DRUGSTORE | C7: 4807770121326 | D7: OTC MONDE SPECIAL MAMON CLASSIC 43G | E7: 12 | F7: PCS
A8: 46182 | B8: PROS MARKETING & PHARMAPLUS DRUGSTORE | C8: 750515030152 | D8: OTC SKYFLAKES GARLIC 25G | E8: 10 | F8: PCS
A9: 46182 | B9: PROS MARKETING & PHARMAPLUS DRUGSTORE | C9: 750515030176 | D9: OTC SKYFLAKES ONION & CHIVES 25G | E9: 10 | F9: PCS
A10: 46182 | B10: PROS MARKETING & PHARMAPLUS DRUGSTORE | C10: 750515031067 | D10: OTC SKYFLAKES SWEET BUTTER 30G | E10: 10 | F10: PCS
A11: 46182 | B11: PROS MARKETING & PHARMAPLUS DRUGSTORE | C11: 750515031029 | D11: OTC SKYFLAKES TSOKOLATE | E11: 10 | F11: PCS
A12: 46183 | B12: AS-LS DISTRIBUTOR | C12: 4806502720172 | D12: GAR BUTTER TOAST 2-SLICE PACK 50G | E12: 10 | F12: PCS
A13: 46190 | B13: EDELIAS MARKETING | C13: 4800116099006 | D13: OTC BUTTER CREAM ENSAYMADA 25G | E13: 10 | F13: PCS
A14: 46190 | B14: EDELIAS MARKETING | C14: 4800116077004 | D14: OTC BUTTER CREAM CHOCOLATE CRACKERS 25G | E14: 10 | F14: PCS
A15: 46190 | B15: EDELIAS MARKETING | C15: 888123456782039 | D15: OTC SUPERLAMIG PEPPERMINT | E15: 50 | F15: PCS
... A20: 46197 | B20: PROS MARKETING & PHARMAPLUS DRUGSTORE | C20: 750515031043 | D20: OTC SKYFLAKES CONDENSADA | E20: 10 | F20: PCS
A21: ADJUSTMENT SHORT
C22: 4800888158925 | D22: REXONA WOMEN DEO-ROLL ON POWDER DRY 25ML | E22: 1
C23: 00006 | D23: CONVIE COKE IN CAN ORIGINAL 320ML | E23: 1
C24: 4800016087608 | D24: MAGIC CREAM BUTTER 28GX10 | E24: 1
C25: 888123456781858 | D25: OTC DYNAMITE MELON MINT RETAIL | E25: 11
C26: 4800142118290 | D26: EMPERADOR DOUBLE LIGHT 1L | E26: 48
C27: 4800067600474 | D27: ALBATROSS KIWI 50G | E27: 1
C28: 4902430381765 | D28: SAFEGUARD IVORY WHITE CARE 135G | E28: 1
C29: 4800034017441 | D29: HAPEE TOOTPASTE BLUE CHILL 55G | E29: 4
E30: =SUM(E4:E29) -> 416

Sheet PULL OUT-
A1: PULL OUT
A2: =PRINTING!B2 -> AS OF JUNE 2026
A3: RETAIL
A4: DATE | B4: SUPPLIER | C4: BARCODE | D4: PARTICULAR | E4: QTY | F4: UNIT
A5: 46178 | B5: KIMBERLIN ENTERPRISES | C5: 4800016304019 | D5: MAXX CHERRY 200G | E5: 1 | F5: PACK
A6: 46178 | B6: KIMBERLIN ENTERPRISES | C6: 4800016307041 | D6: DYNAMITE CHOCO MINT CANDY 200G | E6: 1 | F6: PACK
A7: 46178 | B7: PROS MARKETING & PHARMAPLUS DRUGSTORE | C7: 750515030251 | D7: SKYFLAKES ONION& CHIVES 10S | E7: 1 | F7: PACK
A8: 46178 | B8: PROS MARKETING & PHARMAPLUS DRUGSTORE | C8: 4807770121661 | D8: MONDE SPECIAL MAMON CLASSIC SAVER PACK 12X43G | E8: 1 | F8: PACK
A9: 46182 | B9: PROS MARKETING & PHARMAPLUS DRUGSTORE | C9: 750515030206 | D9: SKYFLAKES GARLIC 10S 250G | E9: 1 | F9: PACK
A10: 46182 | B10: PROS MARKETING & PHARMAPLUS DRUGSTORE | C10: 750515030251 | D10: SKYFLAKES ONION& CHIVES 10S | E10: 1 | F10: PACK
A11: 46182 | B11: PROS MARKETING & PHARMAPLUS DRUGSTORE | C11: 750515031555 | D11: SKYFLAKES MANTIKILYA 30GX10S | E11: 1 | F11: PACK
A12: 46182 | B12: PROS MARKETING & PHARMAPLUS DRUGSTORE | C12: 750515031517 | D12: SKYFLAKES TSOKOLATE 30GX10S | E12: 1 | F12: PACK
A13: 46183 | B13: AS-LS DISTRIBUTOR | C13: 4806502720189 | D13: GAR BUTTER TOAST 2-SLICE PACK 50GX10 | E13: 1 | F13: PACK
A14: 46190 | B14: EDELIAS MARKETING | C14: 4800116099020 | D14: BUTTER CREAM ENSAYMADA CRACKERS 10X25G | E14: 1 | F14: PACK
A15: 46190 | B15: EDELIAS MARKETING | C15: 4800116077028 | D15: BUTTER CREAM CHOCOLATE CRACKERS 10X25G | E15: 1 | F15: PACK
A16: 46190 | B16: EDELIAS MARKETING | C16: 4800620110051 | D16: SUPERLAMIG CANDY | E16: 1 | F16: PACK
... A21: 46197 | B21: PROS MARKETING & PHARMAPLUS DRUGSTORE | C21: 750515030206 | D21: SKYFLAKES GARLIC 10S 250G | E21: 1 | F21: PACK
A23: PULL OUR BAD ORDER | C23: ACTUAL
A24: 46178 | B24: WING-AN MARKETING INC. | C24: 4801234108021 | D24: BAYGON MULTI INSECT KILLER KILLING ACTION 500ML | E24: 1
C25: 4801234108229 | D25: BAYGON MULTI INSECT KILLER WATERBASED 500ML | E25: 1
C26: 4801234107727 | D26: BAYGON MULTI INSECT KILLER ODORLESS 500ML | E26: 4
C27: 4801234107826 | D27: BAYGON SHIELD PROTECTOR 500ML | E27: 5
A28: 46182 | B28: AS-LS DISTRIBUTOR | C28: 4806502721452 | D28: GAR HIGH FIBER WHEAT BREAD 400G | E28: 1
C29: 4806502720165 | D29: GAR DOUBLE DELIGHTS (UBE & CHEESE) 400G | E29: 1
C30: 4806502720080 | D30: GAR PREMIUM PANDESAL 350G | E30: 1
C31: 4806502726907 | D31: GAR NEUBAKE CLASSIC WHITE BREAD SUPER SLICE 300G | E31: 2
C32: 4806502725726 | D32: GAR SOFT DELIGHT PANDESAL 300G | E32: 1
C33: 4806502720080 | D33: GAR PREMIUM PANDESAL 350G | E33: 1
C34: 4806502726914 | D34: GAR NEUBAKE WHEATEN BREAD SUPER SLICE 300G | E34: 1
B35: ROVEN 168 CORP | C35: 8851932478502 | D35: WALLS BITES STRAW YOGHURT 14G | E35: 9
C36: 4800086044372 | D36: SEL BDAY BASO CHOCO 400ML | E36: 2
C37: 4800086047472 | D37: SEL BOOM BOOM COOKIES & CREAM 60ML | E37: 7
C38: 4800086045751 | D38: SEL BOOM BOOM CHOCOLATE 60ML | E38: 5
C39: 4800086045676 | D39: SEL CORNETTO DISC WHITE CHOCO COOKIES & CREAM 115ML | E39: 14
C40: 4800086046482 | D40: SEL CORNETTO DISC BLACK CHOCO COOKIE 115ML | E40: 20
C41: 4800086134325 | D41: SEL CORNETTO CLASSIC CHOCO 110ML | E41: 29
C42: 4800086043306 | D42: SEL CORNETTO COOKIES & DREAM 110ML | E42: 6
C43: 4800086034670 | D43: SEL CORNETTO VANILLA 110ML | E43: 16
C44: 4800086049452 | D44: SELECTA COOKIES N CREAM 100ML | E44: 12
C45: 8999999035624 | D45: MAGNUM MINI VANILLA CLASSIC 45ML | E45: 36
C46: 8999999035631 | D46: MAGNUM MINI VANILLA ALMOND 45ML | E46: 36
C47: 4800086040886 | D47: SEL SUP ROCKY ROAD 750ML | E47: 1
... C50: 4800086050649 | D50: SEL CORNETTO APPLE CRUMBLE 110ML | E50: 8
B51: PADSA ENTERPRISES CORPORATION | C51: 4806500807516 | D51: MAGIC DRI CLOTHLIKE XXL 4S | E51: 76
C52: 4800274040018 | D52: QUAKER INSTANT OATMEAL 400G | E52: 1
C53: 4806500807110 | D53: MAGIC DRI YELLOW SMALL 4S | E53: 21
C54: 4806500806410 | D54: MAGIC DRI PINK XL 4S | E54: 1
C55: 4806500806311 | D55: MAGIC DRI BLUE LARGE 4S | E55: 1
C56: 4806500807028 | D56: MAGIC DRI ORANGE XXL 10S | E56: 6
C57: 4806500807127 | D57: MAGIC DRI YELLOW SMALL 10S | E57: 4
C58: 4806500807158 | D58: MAGIC DRI YELLOW NB-SMALL 30PCS+4FREE | E58: 2
C59: 4806500807561 | D59: MAGIC DRI ORANGE XXL 45PCS+6FREE | E59: 1
B60: MIDLANDS DISTRIBUTION, INC. | C60: 7622300501525 | D60: CHEEZ WHIZ ORIGINAL 62G | E60: 5
C61: 4808647010057 | D61: CHEEZ WHIZ PIMIENTO 220G | E61: 1
B62: KIMBERLIN ENTERPRISES | C62: 4800016307041 | D62: DYNAMITE CHOCO MINT CANDY 200G | E62: 15
C63: 4800016303081 | D63: MAXX DALANDAN ORANGE 200G | E63: 8
C64: 4800016307102 | D64: DYNAMITE MELON MINT FLAVORED CANDY 200G | E64: 11
C65: 4800016307010 | D65: MAXX EUCALYPTUS MENTHOL CANDY 200G | E65: 8
C66: 4800016476013 | D66: X.O. BUTTER CARAMEL CANDY 175G | E66: 11
C67: 4800016305016 | D67: MAXX HONEY MANSI 200G | E67: 1
C68: 4800016475016 | D68: X.O. COFFEE CANDY 175G | E68: 5
C69: 4800016560910 | D69: NISSIN RAMEN SPICY SEAFOOD 59G | E69: 2
C70: 4800016560910 | D70: NISSIN RAMEN SPICY SEAFOOD 59G | E70: 17
C71: 4800016551857 | D71: NISSIN CUP NOODLES SPICY SEAFOOD 40G | E71: 36
C72: 4800016561429 | D72: NISSIN RAMEN CREAMY SEAFOOD 63G | E72: 36
C73: 4800016552113 | D73: NISSIN CUP NOODLES SEAFOOD 40G | E73: 17
C74: 4800016552274 | D74: NISSIN CUP NOODLES BULALO 40G | E74: 7
... C82: 4800016087585 | D82: MAGIC CREAM CONDENSADA CREAM 28GX10 | E82: 2
C83: 87608 | D83: MAGIC CREAM BUTTER | E83: 1
C84: 4800010075564 | D84: CREAM-O CHOCO FUDGE 300G | E84: 2
C85: 4800016112577 | D85: JNJ CREAM-O CHOCOLATE CAKE SANDWICH W/ THICK VANILLA | E85: 3
C86: 4800016077531 | D86: CREAM-O COOKIES N CREAM 27GX10 | E86: 4
C87: 4800010075526 | D87: CREAM-O VANILLA 300G | E87: 2
C88: 4800016306013 | D88: MAXX HONEY LEMON 200G | E88: 3
B89: MAKOBOBI DISTRIBUTORS INC. | C89: 4800016022180 | D89: GREAT TASTE WHITE CREMA TWINPACK 50G | E89: 120
B90: MIDLANDS DISTRIBUTION, INC. | C90: 8992760221066 | D90: OREO VANILLA ORIGINAL 12X27.6G | E90: 2
B91: AS-LS DISTRIBUTOR | C91: 4806502726822 | D91: GAR NEUBAKE WHITE BREAD 450G | E91: 1
C92: 4806502726822 | D92: GAR NEUBAKE WHITE BREAD 450G | E92: 2
C93: 4806502726914 | D93: GAR NEUBAKE WHEATEN BREAD SUPER SLICE 300G | E93: 1
E94: =SUM(E5:E93) -> 1090
